{"0":["Pitch","high-gain","Yaw","FLIGHT","CAPCOM"],"1":["FLIGHT"],"2":["Roll","CAPCOM"],"3":["FLIGHT"],"4":["FLIGHT","EECOM"],"5":["FLIGHT","EECOM"],"6":["EECOM"],"7":["FLIGHT"],"8":["Cryo","EECOM"],"9":["FLIGHT"],"10":["EECOM"],"11":["FLIGHT","GNC"],"12":["FLIGHT","GNC"],"13":["Quads","GNC"],"14":["FLIGHT"],"15":["GNC"],"16":["FLIGHT"],"17":["GNC"],"18":["Quads","FLIGHT"],"19":["Jet","GNC"],"20":["FLIGHT","CAPCOM"],"21":["CAPCOM"],"22":["FLIGHT","INCO"],"23":["FLIGHT","INCO"],"24":["high-gain","INCO"],"25":["FLIGHT"],"26":["INCO"],"27":["Roll","FLIGHT"],"28":["high-gain","FLIGHT","CAPCOM"],"29":["INCO"],"30":["FLIGHT"],"31":["CSM","high-gain","FLIGHT","CAPCOM"],"32":["INCO"],"33":["FLIGHT"],"34":["FLIGHT"],"35":["FLIGHT","GNC"],"36":["FLIGHT","GNC"],"37":["C-4","GNC"],"38":["FLIGHT"],"39":["GNC"],"40":["C-4","FLIGHT","CAPCOM"],"41":["FLIGHT","EECOM"],"42":["FLIGHT","EECOM"],"43":["EECOM"],"44":["FLIGHT"],"45":["FLIGHT","EECOM"],"46":["FLIGHT"],"47":["FLIGHT","TELMU"],"48":["FLIGHT","TELMU"],"49":["Current","TELMU"],"50":["FLIGHT"],"51":["TLC","TELMU"],"52":["FLIGHT"],"53":["FLIGHT","GUIDO"],"54":["FLIGHT"],"55":["Docking Index","GUIDO"],"56":["FLIGHT","CAPCOM"],"57":["FLIGHT"],"58":["FLIGHT","GUIDO"],"59":["FLIGHT"],"60":["FLIGHT","GNC"],"61":["FLIGHT","GNC"],"62":["H2","O2","FLIGHT","CAPCOM"],"63":["CAPCOM"],"64":["FLIGHT","GUIDO"],"65":["FLIGHT"],"66":["GUIDO"],"67":["FLIGHT"],"68":["GUIDO"],"69":["DSKY","FLIGHT"],"70":["GUIDO"],"71":["Attitude","FLIGHT"],"72":["FLIGHT","GNC"],"73":["FLIGHT"],"74":["FLIGHT","GUIDO"],"75":["FLIGHT"],"76":["P00","GUIDO"],"77":["FLIGHT"],"78":["GUIDO"],"79":["GUIDO"],"80":["FLIGHT"],"81":["GUIDO"],"82":["FLIGHT","TELMU"],"83":["FLIGHT","TELMU"],"84":["Current","TELMU"],"85":["FLIGHT"],"86":["FLIGHT","GUIDO"],"87":["FLIGHT"],"88":["GUIDO"],"89":["FLIGHT","GNC"],"90":["FLIGHT","CAPCOM"],"91":["AC bus","Undervolt","FLIGHT","EECOM"],"92":["FLIGHT","EECOM"],"93":["FLIGHT"],"94":["MAIN B","Undervolt","CAPCOM"],"95":["FLIGHT","EECOM"],"96":["FLIGHT"],"97":["FLIGHT","EECOM"],"98":["FLIGHT"],"99":["FLIGHT","INCO"],"100":["FLIGHT","INCO"],"101":["Wide Beam","INCO"],"102":["FLIGHT"],"103":["Wide Beam","FLIGHT","INCO"],"104":["INCO"],"105":["Wide Beam","FLIGHT","INCO"],"106":["INCO"],"107":["CAPCOM"],"108":["FLIGHT","TELMU"],"109":["Current","FLIGHT"],"110":["FLIGHT"],"111":["FLIGHT","EECOM"],"112":["FLIGHT","EECOM"],"113":["FLIGHT","EECOM"],"114":["FLIGHT"],"115":["FLIGHT"],"116":["SIG SENSOR","FLIGHT"],"117":["FLIGHT","EECOM"],"118":["FLIGHT"],"119":["MAIN A","MAIN B","Fuel cell","EECOM"],"120":["FLIGHT","Fuel cell","MAIN A","MAIN B"],"121":["EECOM","MAIN A","MAIN B","Fuel cell"],"122":["EECOM"],"123":["FLIGHT"],"124":["AC bus","AC 2","MAIN B","EECOM","Fuel cell","FLIGHT"],"125":["FLIGHT"],"126":["FLIGHT"],"127":["FLIGHT"],"128":["FLIGHT","GNC"],"129":["EECOM"],"130":["FLIGHT","GNC"],"131":["Helium","Quad","GNC"],"132":["Attitude","BI","FLIGHT"],"133":["Helium","Jets","GNC"],"134":["Helium","Quad","FLIGHT"],"135":["Quad","GNC"],"136":["Helium","Quad","FLIGHT"],"137":["GNC"],"138":["Helium","Quad","FLIGHT","CAPCOM"],"139":["RCS","FLIGHT"],"140":["CAPCOM"],"141":["MAIN A","MAIN B","Fuel cell","FLIGHT"],"142":["FLIGHT","EECOM"],"143":["high-gain","FLIGHT","INCO"],"144":["Wide Beam","FLIGHT","INCO"],"145":["FLIGHT"],"146":["FLIGHT","EECOM"],"147":["EECOM"],"148":["CAPCOM"],"149":["FLIGHT","EECOM"],"150":["FLIGHT","EECOM"],"151":["EECOM"],"152":["MAIN A","FLIGHT"],"153":["MAIN A","Fuel cell","FLIGHT","EECOM"],"154":["FLIGHT"],"155":["FLIGHT"],"156":["MAIN B","MAIN A","Fuel cell","EECOM"],"157":["MAIN B","Fuel cell","FLIGHT"],"158":["Fuel cell","EECOM"],"159":["Fuel cell","FLIGHT","EECOM"],"160":["MAIN A","FLIGHT"],"161":["FLIGHT"],"162":["EECOM"],"163":["MAIN A","FLIGHT"],"164":["Amps","Fuel cell","EECOM"],"165":["FLIGHT"],"166":["AC bus","MAIN B","EECOM"],"167":["AC bus","FLIGHT"],"168":["FLIGHT","EECOM"],"169":["FLIGHT"],"170":["FLIGHT","EECOM"],"171":["FLIGHT","EECOM"],"172":["MAIN A","EECOM"],"173":["FLIGHT"],"174":["FLIGHT","EECOM"],"175":["FLIGHT","INCO"],"176":["FLIGHT","INCO"],"177":["AC 2","high-gain","INCO"],"178":["FLIGHT"],"179":["INCO"],"180":["FLIGHT"],"181":["210s","INCO"],"182":["210s","FLIGHT","CAPCOM"],"183":["INCO"],"184":["INCO"],"185":["INCO"],"186":["OMNI Charlie","CAPCOM"],"187":["FLIGHT"],"188":["INCO"],"189":["OMNI Charlie","FLIGHT","INCO"],"190":["210s","FLIGHT"],"191":["INCO"],"192":["FLIGHT","EECOM"],"193":["FLIGHT","EECOM"],"194":["Fuel cell","EECOM","O2"],"195":["FLIGHT"],"196":["Fuel cell","FLIGHT"],"197":["EECOM"],"198":["O2","EECOM"],"199":["O2","FLIGHT","CAPCOM"],"200":["FLIGHT","GUIDO"],"201":["FLIGHT"],"202":["GUIDO"],"203":["RCS","FLIGHT"],"204":["FLIGHT","GNC"],"205":["FLIGHT","GNC"],"206":["GNC"],"207":["Helium","Quad","FLIGHT"],"208":["FLIGHT","GNC"],"209":["RCS","FLIGHT"],"210":["Attitude","MAIN A","GNC"],"211":["RCS","FLIGHT"],"212":["GNC"],"213":["Attitude","FLIGHT"],"214":["GNC"],"215":["FLIGHT","TELMU"],"216":["FLIGHT","TELMU"],"217":["Current","TELMU"],"218":["FLIGHT"],"219":["CAPCOM"],"220":["RCS","FLIGHT"],"221":["Jets","GNC"],"222":["FLIGHT"],"223":["FLIGHT","CAPCOM"],"224":["FLIGHT"],"225":["FLIGHT","EECOM"],"226":["FLIGHT","EECOM"],"227":["FLIGHT"],"228":["Fuel cell","EECOM"],"229":["Fuel cell","Open-circuit","FLIGHT"],"230":["EECOM"],"231":["Fuel cell","Open-circuit","FLIGHT","CAPCOM"],"232":["Open-circuit","CAPCOM"],"233":["FLIGHT","CAPCOM","EECOM"],"234":["FLIGHT","EECOM"],"235":["Open-circuit","FLIGHT"],"236":["FLIGHT","EECOM"],"237":["EECOM"],"238":["Open-circuit","FLIGHT","CAPCOM"],"239":["FLIGHT","GNC"],"240":["FLIGHT","EECOM"],"241":["FLIGHT"],"242":["FLIGHT"],"243":["FLIGHT","EECOM"],"244":["FLIGHT","CAPCOM"],"245":["FLIGHT"],"246":["FLIGHT","GNC"],"247":["FLIGHT","GNC"],"248":["FLIGHT","EECOM"],"249":["FLIGHT","EECOM"],"250":["FLIGHT","EECOM"],"251":["FLIGHT"],"252":["FLIGHT","EECOM"],"253":["FLIGHT","EECOM"],"254":["FLIGHT"],"255":["EECOM"],"256":["FLIGHT"],"257":["FLIGHT","INCO"],"258":["FLIGHT","INCO"],"259":["INCO"],"260":["FLIGHT"],"261":["CSM","Fuel cell","O2","RCS","FLIGHT"],"262":["FLIGHT","GNC"],"263":["FLIGHT","GNC"],"264":["Jet","GNC"],"265":["FLIGHT"],"266":["FLIGHT"],"267":["MAIN A","GNC"],"268":["FLIGHT"],"269":["MAIN A","Quad","GNC"],"270":["FLIGHT"],"271":["GNC"],"272":["FLIGHT","GNC"],"273":["Jet","GNC"],"274":["FLIGHT"],"275":["FLIGHT","GUIDO"],"276":["FLIGHT"],"277":["Gimbal lock","GUIDO"],"278":["MAIN A","Gimbal lock","C-3","C-4","B-3","B-4","C-1","C-2","FLIGHT","CAPCOM"],"279":["FLIGHT"],"280":["GUIDO"],"281":["Coarse Align","FLIGHT"],"282":["P52","GUIDO"],"283":["P52","FLIGHT"],"284":["GUIDO"],"285":["Coarse Align","FLIGHT"],"286":["Coarse Align","GUIDO"],"287":["FLIGHT"],"288":["FLIGHT","EECOM"],"289":["FLIGHT","EECOM"],"290":["FLIGHT"],"291":["FLIGHT"],"292":["EECOM"],"293":["TM","FLIGHT"],"294":["EECOM"],"295":["FLIGHT","INCO"],"296":["FLIGHT"],"297":["INCO"],"298":["FLIGHT"],"299":["FLIGHT","CAPCOM"],"300":["FLIGHT"],"301":["Amps","FLIGHT","EECOM"],"302":["FLIGHT","INCO"],"303":["FLIGHT","EECOM"],"304":["Amps","FLIGHT","EECOM"],"305":["Amps","FLIGHT"],"306":["EECOM"],"307":["FLIGHT"],"308":["Amps","FLIGHT","CAPCOM"],"309":["FLIGHT","GNC"],"310":["FLIGHT","GNC"],"311":["PTC","GNC"],"312":["FLIGHT"],"313":["GNC"],"314":["FLIGHT"],"315":["GNC"],"316":["Amps","CAPCOM"],"317":["Amps","FLIGHT","CAPCOM"],"318":["FLIGHT","EECOM"],"319":["FLIGHT","EECOM"],"320":["Fuel cell","Fuel Cell Pumps","FLIGHT"],"321":["FLIGHT"],"322":["Fuel cell","FLIGHT","EECOM"],"323":["FLIGHT"],"324":["FLIGHT","EECOM"],"325":["FLIGHT","EECOM"],"326":["PTC","EECOM"],"327":["FLIGHT"],"328":["EECOM"],"329":["FLIGHT"],"330":["FLIGHT","EECOM"],"331":["FLIGHT","EECOM"],"332":["Quad","GNC"],"333":["EECOM"],"334":["GNC"],"335":["FLIGHT","GNC"],"336":["FLIGHT","GNC"],"337":["GNC"],"338":["CMC","FLIGHT"],"339":["PTC","GNC"],"340":["CMC","FLIGHT"],"341":["GNC"],"342":["GNC"],"343":["Attitude","FLIGHT"],"344":["VERB 49","FLIGHT","GNC"],"345":["FLIGHT","EECOM"],"346":["FLIGHT","EECOM"],"347":["AC 2","Amps","O2","EECOM"],"348":["FLIGHT"],"349":["AC 2","MAIN A","Inverter","EECOM"],"350":["EECOM"],"351":["FLIGHT"],"352":["MAIN A","Inverter","FLIGHT","EECOM"],"353":["FLIGHT"],"354":["FLIGHT","EECOM"],"355":["Attitude","PTC","Rate Damping","FLIGHT","CAPCOM"],"356":["Amperage","CAPCOM"],"357":["FLIGHT","EECOM"],"358":["FLIGHT","INCO"],"359":["FLIGHT"],"360":["PTC","high-gain","INCO"],"361":["FLIGHT","GNC"],"362":["CAPCOM","GNC"],"363":["GNC"],"364":["PTC","FLIGHT"],"365":["FLIGHT","GNC"],"366":["FLIGHT","EECOM"],"367":["FLIGHT","EECOM"],"368":["AC buses","Inverter","EECOM"],"369":["Inverter","FLIGHT"],"370":["AC bus","AC 2","Fuel cell","EECOM"],"371":["Fuel cell","Fuel Cell Pumps","FLIGHT"],"372":["AC 2","Fuel cell","EECOM"],"373":["BMAG","Fuel cell","Fuel Cell Pump","FLIGHT"],"374":["EECOM"],"375":["AC buses","Inverter","FLIGHT"],"376":["FLIGHT","EECOM"],"377":["AC 2","MAIN A","Inverter","FLIGHT","CAPCOM"],"378":["FLIGHT"],"379":["CAPCOM"],"380":["AC buses","Inverter","FLIGHT","CAPCOM","EECOM"],"381":["CAPCOM"],"382":["FLIGHT","EECOM"],"383":["FLIGHT","EECOM"],"384":["FLIGHT"],"385":["EECOM"],"386":["FLIGHT","CONTROL","TELMU"],"387":["FLIGHT","TELMU"],"388":["FLIGHT","CONTROL"],"389":["FLIGHT"],"390":["FLIGHT","CONTROL"],"391":["TELMU"],"392":["FLIGHT"],"393":["CONTROL"],"394":["FLIGHT","FDO"],"395":["FLIGHT","FDO"],"396":["FDO"],"397":["FLIGHT"],"398":["FLIGHT","CAPCOM"],"399":["Fuel cell","FLIGHT","EECOM"],"400":["FLIGHT"],"401":["AC 1","Fuel cell","EECOM"],"402":["AC 1","Fuel cell","FUEL CELL 2 PUMP","FLIGHT"],"403":["EECOM"],"404":["AC 1","Fuel cell","FUEL CELL 2 PUMP","FLIGHT","CAPCOM"],"405":["FLIGHT","EECOM"],"406":["FLIGHT","EECOM"],"407":["FLIGHT"],"408":["FLIGHT","NETWORK"],"409":["FLIGHT","NETWORK"],"410":["RTCC","FLIGHT"],"411":["RTCC","NETWORK"],"412":["RTCC","FLIGHT"],"413":["NETWORK"],"414":["Rates","FLIGHT","CAPCOM"],"415":["FLIGHT","GNC"],"416":["GNC"],"417":["FLIGHT"],"418":["C-3","FLIGHT","GNC"],"419":["Rates","FLIGHT"],"420":["Rates","GNC"],"421":["FLIGHT"],"422":["DIRECT","Pitch","Rates","Roll","CAPCOM"],"423":["FLIGHT"],"424":["CAPCOM"],"425":["FLIGHT","GNC"],"426":["FLIGHT"],"427":["FLIGHT","GNC"],"428":["FLIGHT"],"429":["CAPCOM"],"430":["FLIGHT"],"431":["OMNI Charlie","FLIGHT","INCO"],"432":["OMNI Charlie","FLIGHT","CAPCOM"],"433":["AC buses","FLIGHT","EECOM"],"434":["FLIGHT","EECOM"],"435":["FLIGHT"],"436":["FLIGHT","CAPCOM"],"437":["FLIGHT","TELMU"],"438":["FLIGHT"],"439":["FLIGHT","FDO"],"440":["FLIGHT","FDO"],"441":["RTCC","FDO"],"442":["FLIGHT"],"443":["FLIGHT","GNC"],"444":["FLIGHT","GNC"],"445":["MAIN A","Pitch","GNC"],"446":["RCS","FLIGHT"],"447":["Pitch","FLIGHT","GNC"],"448":["FLIGHT"],"449":["MAIN A","GNC"],"450":["MAIN A","FLIGHT"],"451":["FLIGHT","CAPCOM"],"452":["RCS","FLIGHT","GNC"],"453":["FLIGHT","GNC"],"454":["FLIGHT"],"455":["FLIGHT","GNC"],"456":["EECOM"],"457":["FLIGHT","EECOM"],"458":["MAIN B","O2","EECOM"],"459":["FLIGHT"],"460":["FLIGHT"],"461":["BMAG","EECOM"],"462":["BMAG","FLIGHT"],"463":["EECOM"],"464":["FLIGHT"],"465":["BMAG","SCS","EECOM"],"466":["Amps","FLIGHT"],"467":["BMAG","EECOM"],"468":["BMAG","FLIGHT","CAPCOM"],"469":["FLIGHT"],"470":["EECOM"],"471":["FLIGHT"],"472":["Fuel cell","EECOM"],"473":["FLIGHT"],"474":["Fuel cell","EECOM"],"475":["Fuel cell","Open-circuit","CAPCOM"],"476":["Fuel cell","Open-circuit","EECOM"],"477":["Fuel cell","Open-circuit","FLIGHT"],"478":["EECOM"],"479":["FLIGHT","GNC"],"480":["FLIGHT"],"481":["FLIGHT","GNC"],"482":["FLIGHT"],"483":["Jet","RCS","GNC"],"484":["FLIGHT"],"485":["MAIN A","Jets","GNC"],"486":["MAIN A","FLIGHT"],"487":["GNC"],"488":["MAIN A","Jets","FLIGHT","CAPCOM"],"489":["CAPCOM"],"490":["FLIGHT","EECOM"],"491":["FLIGHT","EECOM"],"492":["EECOM"],"493":["FLIGHT","Cryo","Fuel cell","O2"],"494":["EECOM"],"495":["FLIGHT","EECOM"],"496":["Cryo","O2","FLIGHT"],"497":["FLIGHT","EECOM"],"498":["FLIGHT"],"499":["FLIGHT","EECOM"],"500":["FLIGHT"],"501":["EECOM"],"502":["FLIGHT"],"503":["FLIGHT","EECOM"],"504":["FLIGHT"],"505":["MAIN B","O2","EECOM"],"506":["FLIGHT","CAPCOM"],"507":["FLIGHT","EECOM"],"508":["FLIGHT","EECOM"],"509":["Cryo","Surge Tank","EECOM"],"510":["FLIGHT"],"511":["EECOM"],"512":["FLIGHT"],"513":["FLIGHT"],"514":["Cryo","EECOM"],"515":["Fuel cell","FLIGHT"],"516":["Surge Tank","FLIGHT","EECOM"],"517":["FLIGHT"],"518":["EECOM"],"519":["Surge Tank","FLIGHT","CAPCOM"],"520":["Surge Tank","CAPCOM"],"521":["FLIGHT"],"522":["O2","Surge Tank","CAPCOM"],"523":["FLIGHT"],"524":["FLIGHT"],"525":["FLIGHT","EECOM"],"526":["FLIGHT","EECOM"],"527":["FLIGHT","EECOM"],"528":["FLIGHT"],"529":["Amps","O2 TANK 1 HEATERS","MAIN A","O2","EECOM"],"530":["MAIN A","FLIGHT"],"531":["FLIGHT","EECOM"],"532":["FLIGHT","EECOM"],"533":["Amps","O2 TANK 1 HEATERS","MAIN A","O2","EECOM"],"534":["O2","FLIGHT"],"535":["EECOM"],"536":["CRYOGENIC O2 HEATER 1","O2","FLIGHT","EECOM"],"537":["FLIGHT","GNC"],"538":["FLIGHT","CAPCOM"],"539":["Cryo","O2","FLIGHT","CAPCOM"],"540":["Amps","MAIN A","FLIGHT"],"541":["FLIGHT","EECOM"],"542":["Current","FLIGHT","EECOM"],"543":["FLIGHT","EECOM"],"544":["FLIGHT"],"545":["EECOM"],"546":["FLIGHT"],"547":["FLIGHT","EECOM"],"548":["FLIGHT"],"549":["FLIGHT","AFD"],"550":["FLIGHT","AFD"],"551":["FLIGHT"],"552":["FLIGHT","AFD"],"553":["FLIGHT"],"554":["AFD"],"555":["FLIGHT"],"556":["FLIGHT"],"557":["FLIGHT","CONTROL","TELMU"],"558":["FLIGHT","CONTROL"],"559":["FLIGHT"],"560":["CONTROL"],"561":["FLIGHT","EECOM"],"562":["FLIGHT","EECOM"],"563":["O2","EECOM"],"564":["FLIGHT"],"565":["EECOM"],"566":["FLIGHT"],"567":["FLIGHT","EECOM"],"568":["FLIGHT","CAPCOM"],"569":["FLIGHT","EECOM"],"570":["FLIGHT"],"571":["EECOM"],"572":["FLIGHT","GNC"],"573":["FLIGHT","GNC"],"574":["GNC"],"575":["Quad","FLIGHT"],"576":["FLIGHT","GNC"],"577":["FLIGHT"],"578":["Pitch","Roll","Yaw","GNC"],"579":["FLIGHT"],"580":["FLIGHT","EECOM"],"581":["FLIGHT","EECOM"],"582":["Fuel cell","O2","EECOM"],"583":["FLIGHT"],"584":["Current","FLIGHT","EECOM"],"585":["Current","FLIGHT"],"586":["FLIGHT","EECOM"],"587":["PCM","FLIGHT"],"588":["MAIN A","O2","EECOM"],"589":["Cryo","O2","FLIGHT"],"590":["MAIN A","O2","EECOM"],"591":["FLIGHT"],"592":["FLIGHT","EECOM"],"593":["FLIGHT"],"594":["Cryo","EECOM"],"595":["FLIGHT","CAPCOM"],"596":["Cryo","MAIN A","O2","CAPCOM"],"597":["FLIGHT"],"598":["FLIGHT","EECOM"],"599":["FLIGHT","TELMU"],"600":["FLIGHT","TELMU"],"601":["FLIGHT"],"602":["TELMU"],"603":["FLIGHT"],"604":["FLIGHT","CAPCOM"],"605":["FLIGHT"],"606":["FLIGHT","EECOM"],"607":["FLIGHT","EECOM"],"608":["EECOM"],"609":["FLIGHT","CAPCOM"],"610":["FLIGHT","EECOM"],"611":["FLIGHT","EECOM"],"612":["FLIGHT","CAPCOM"],"613":["FLIGHT","CAPCOM"],"614":["FLIGHT","CAPCOM"],"615":["FLIGHT"],"616":["CAPCOM"],"617":["FLIGHT"],"618":["Talkbacks","CAPCOM"],"619":["FLIGHT"],"620":["FLIGHT","FDO"],"621":["FLIGHT","EECOM"],"622":["FLIGHT","EECOM"],"623":["O2","FLIGHT"],"624":["FLIGHT","EECOM"],"625":["FLIGHT"],"626":["EECOM"],"627":["FLIGHT","FDO"],"628":["FLIGHT","FDO"],"629":["SPS","FLIGHT"],"630":["FLIGHT","FDO"],"631":["CSM","DPS","RCS","FLIGHT"],"632":["FDO"],"633":["FLIGHT"],"634":["FLIGHT","FDO"],"635":["FLIGHT"],"636":["FLIGHT","GUIDO"],"637":["FLIGHT","EECOM"],"638":["FLIGHT","EECOM"],"639":["Fuel cell","O2","EECOM"],"640":["FLIGHT"],"641":["Fuel cell","FLIGHT","EECOM"],"642":["FLIGHT","GNC"],"643":["FLIGHT","GNC"],"644":["GNC"],"645":["FLIGHT"],"646":["GNC"],"647":["C-1","FLIGHT","CAPCOM"],"648":["FLIGHT","CAPCOM"],"649":["C-1","FLIGHT"],"650":["C-1","CAPCOM"],"651":["C-1","FLIGHT"],"652":["FLIGHT","EECOM"],"653":["FLIGHT","EECOM"],"654":["FLIGHT"],"655":["EECOM"],"656":["FLIGHT","EECOM"],"657":["FLIGHT","EECOM"],"658":["EECOM"],"659":["FLIGHT","EECOM"],"660":["FLIGHT","EECOM"],"661":["Fuel cell","FLIGHT"],"662":["FLIGHT","EECOM"],"663":["FLIGHT"],"664":["EECOM"],"665":["Fuel cell","O2","FLIGHT","CAPCOM"],"666":["Fuel cell","FLIGHT","CAPCOM"],"667":["Fuel cell","CAPCOM"],"668":["CAPCOM"],"669":["O2","FLIGHT"],"670":["CAPCOM"],"671":["FLIGHT","GNC"],"672":["FLIGHT","GNC"],"673":["Attitude","Jet","GNC"],"674":["FLIGHT"],"675":["GNC"],"676":["Attitude","FLIGHT"],"677":["FLIGHT","GNC"],"678":["FLIGHT"],"679":["Fuel cell","FLIGHT"],"680":["FLIGHT","EECOM"],"681":["FLIGHT","EECOM"],"682":["Fuel cell","FLIGHT"],"683":["EECOM"],"684":["FLIGHT","CAPCOM"],"685":["Fuel cell","FLIGHT","EECOM"],"686":["Fuel cell","FLIGHT"],"687":["Current","EECOM"],"688":["CAPCOM"],"689":["FLIGHT","INCO"],"690":["INCO"],"691":["FLIGHT","EECOM"],"692":["INCO"],"693":["FLIGHT","EECOM"],"694":["FLIGHT","EECOM"],"695":["FLIGHT"],"696":["EECOM"],"697":["FLIGHT"],"698":["INCO"],"699":["FLIGHT","EECOM","INCO"],"700":["Amps","INCO"],"701":["FLIGHT","CAPCOM"],"702":["CAPCOM"],"703":["FLIGHT"],"704":["CAPCOM"],"705":["FLIGHT"],"706":["FLIGHT","EECOM"],"707":["AFD"],"708":["FLIGHT","CAPCOM"],"709":["FLIGHT","GUIDO"],"710":["FLIGHT"],"711":["06 18","GUIDO"],"712":["FLIGHT","FDO"],"713":["Fuel cell","FLIGHT","CAPCOM"],"714":["FLIGHT"],"715":["CAPCOM"],"716":["FLIGHT"],"717":["FLIGHT","FDO"],"718":["FLIGHT","FDO"],"719":["Checkpoint","FDO"],"720":["Checkpoint","FLIGHT","EECOM","GNC"],"721":["FLIGHT","EECOM"],"722":["FLIGHT","GNC"],"723":["Checkpoint","FLIGHT"],"724":["FLIGHT","EECOM"],"725":["FLIGHT","EECOM"],"726":["FLIGHT"],"727":["EECOM"],"728":["FLIGHT"],"729":["FLIGHT","FDO"],"730":["FLIGHT","EECOM"],"731":["FLIGHT","EECOM"],"732":["Fuel cell","EECOM"],"733":["Fuel cell","FLIGHT"],"734":["EECOM"],"735":["EECOM"],"736":["FLIGHT"],"737":["CAPCOM"],"738":["FLIGHT"],"739":["FLIGHT"],"740":["Barber pole","FLIGHT","EECOM"],"741":["Barber pole","FLIGHT","EECOM"],"742":["FLIGHT","EECOM"],"743":["FLIGHT"],"744":["EECOM"],"745":["FLIGHT"],"746":["Checkpoint","FLIGHT","FDO"],"747":["FLIGHT"],"748":["A-4","FLIGHT","GNC"],"749":["A-4","FLIGHT","CAPCOM"],"750":["OMNI Charlie","FLIGHT","INCO"],"751":["OMNI Charlie","FLIGHT"],"752":["FLIGHT"],"753":["FLIGHT"],"754":["FLIGHT","EECOM"],"755":["FLIGHT","EECOM"],"756":["FLIGHT"],"757":["Barber pole","EECOM"],"758":["Fuel cell","FLIGHT"],"759":["FLIGHT","EECOM"],"760":["Fuel cell","FLIGHT"],"761":["EECOM"],"762":["FLIGHT"],"763":["EECOM"],"764":["FLIGHT","GNC"],"765":["GNC"],"766":["FLIGHT"],"767":["FLIGHT"],"768":["FLIGHT","GNC"],"769":["FLIGHT","GNC"],"770":["Rates","FLIGHT"],"771":["CAPCOM","GNC"],"772":["FLIGHT","GNC"],"773":["FLIGHT"],"774":["ACCEL CMD","GNC"],"775":["ACCEL CMD","FLIGHT"],"776":["GNC"],"777":["FLIGHT"],"778":["FLIGHT","CAPCOM"],"779":["FLIGHT"],"780":["CAPCOM"],"781":["FLIGHT","GNC"],"782":["FLIGHT","GNC"],"783":["FLIGHT"],"784":["GNC"],"785":["ACCEL CMD","Rates","FLIGHT"],"786":["FLIGHT","GNC"],"787":["Rate Damping","FLIGHT"],"788":["GNC"],"789":["BMAG","FLIGHT"],"790":["GNC"],"791":["FLIGHT"],"792":["FLIGHT","EECOM"],"793":["FLIGHT","EECOM"],"794":["CAPCOM"],"795":["EECOM"],"796":["FLIGHT"],"797":["EECOM","Fuel cell"],"798":["FLIGHT"],"799":["Fuel cell","FLIGHT"],"800":["O2","FLIGHT","EECOM"],"801":["EECOM"],"802":["FLIGHT"],"803":["FLIGHT","EECOM"],"804":["FLIGHT"],"805":["FLIGHT","CAPCOM"],"806":["FLIGHT","EECOM"],"807":["FLIGHT","EECOM"],"808":["FLIGHT"],"809":["EECOM"],"810":["FLIGHT"],"811":["FLIGHT","EECOM"],"812":["FLIGHT"],"813":["Fuel cell","EECOM"],"814":["FLIGHT"],"815":["O2","EECOM"],"816":["FLIGHT"],"817":["EECOM"],"818":["FLIGHT"],"819":["Fuel cell","EECOM"],"820":["FLIGHT"],"821":["EECOM"],"822":["Fuel cell","FLIGHT"],"823":["Fuel cell","EECOM"],"824":["FLIGHT"],"825":["EECOM"],"826":["FLIGHT","EECOM"],"827":["FLIGHT","EECOM"],"828":["FLIGHT","EECOM"],"829":["Fuel cell","FLIGHT"],"830":["O2","EECOM"],"831":["FLIGHT"],"832":["FLIGHT"],"833":["EECOM"],"834":["FLIGHT"],"835":["FLIGHT"],"836":["FLIGHT","EECOM"],"837":["FLIGHT"],"838":["EECOM"],"839":["FLIGHT"],"840":["EECOM"],"841":["FLIGHT"],"842":["FLIGHT","EECOM"],"843":["FLIGHT"],"844":["Fuel cell","EECOM"],"845":["Fuel cell","FLIGHT","CAPCOM"],"846":["Fuel cell","CAPCOM"],"847":["FLIGHT","EECOM"],"848":["FLIGHT","EECOM"],"849":["Fuel cell","FLIGHT"],"850":["EECOM"],"851":["FLIGHT"],"852":["CAPCOM"],"853":["FLIGHT"],"854":["CAPCOM"],"855":["FLIGHT","EECOM"],"856":["FLIGHT","EECOM"],"857":["FLIGHT"],"858":["EECOM"],"859":["FLIGHT"],"860":["EECOM"],"861":["FLIGHT","GNC"],"862":["FLIGHT"],"863":["FLIGHT"],"864":["MAIN A","EECOM"],"865":["FLIGHT"],"866":["EECOM"],"867":["MAIN A","Fuel cell","FLIGHT"],"868":["EECOM"],"869":["FLIGHT","INCO"],"870":["FLIGHT"],"871":["INCO"],"872":["FLIGHT"],"873":["FLIGHT","EECOM"],"874":["FLIGHT","EECOM"],"875":["FLIGHT"],"876":["FLIGHT","EECOM"],"877":["FLIGHT"],"878":["FLIGHT","EECOM"],"879":["FLIGHT"],"880":["FLIGHT"],"881":["FLIGHT","EECOM"],"882":["FLIGHT","EECOM"],"883":["FLIGHT","EECOM"],"884":["FLIGHT"],"885":["EECOM"],"886":["FLIGHT"],"887":["FLIGHT","EECOM"],"888":["FLIGHT"],"889":["EECOM"],"890":["FLIGHT","EECOM"],"891":["FLIGHT"],"892":["EECOM"],"893":["Fuel cell","FLIGHT"],"894":["FLIGHT","GNC"],"895":["FLIGHT"],"896":["Roll","GNC"],"897":["FLIGHT"],"898":["GNC","ACCEL CMD"],"899":["FLIGHT"],"900":["FLIGHT"],"901":["GNC"],"902":["Roll","FLIGHT","CAPCOM"],"903":["FLIGHT"],"904":["FLIGHT"],"905":["FLIGHT","EECOM"],"906":["FLIGHT"],"907":["CSM","EECOM"],"908":["TELMU"],"909":["FLIGHT"],"910":["EECOM"],"911":["FLIGHT","CONTROL","TELMU"],"912":["CONTROL"],"913":["FLIGHT"],"914":["FLIGHT","CONTROL"],"915":["FLIGHT"],"916":["FLIGHT","TELMU"],"917":["FLIGHT"],"918":["FLIGHT","INCO"],"919":["FLIGHT"],"920":["high-gain","INCO"],"921":["high-gain","FLIGHT"],"922":["INCO"],"923":["FLIGHT"],"924":["210s","INCO"],"925":["high-gain","FLIGHT","CAPCOM"],"926":["FLIGHT","EECOM"],"927":["FLIGHT"],"928":["EECOM"],"929":["high-gain","FLIGHT"],"930":["EECOM"],"931":["Amps","FLIGHT","EECOM"],"932":["Amps","EECOM"],"933":["Amps","FLIGHT"],"934":["EECOM"],"935":["O2","FLIGHT"],"936":["EECOM"],"937":["FLIGHT","CAPCOM"],"938":["FLIGHT","CAPCOM"],"939":["CMC","FLIGHT"],"940":["FLIGHT","GUIDO"],"941":["FLIGHT","CAPCOM"],"942":["CAPCOM"],"943":["FLIGHT","GUIDO"],"944":["FLIGHT","EECOM"],"945":["FLIGHT","EECOM"],"946":["FLIGHT"],"947":["FLIGHT","EECOM"],"948":["FLIGHT","GUIDO"],"949":["FLIGHT"],"950":["FLIGHT"],"951":["GUIDO"],"952":["FLIGHT"],"953":["FLIGHT","EECOM"],"954":["FLIGHT"],"955":["EECOM"],"956":["FLIGHT"],"957":["FLIGHT","EECOM"],"958":["FLIGHT"],"959":["FLIGHT","EECOM"],"960":["FLIGHT"],"961":["EECOM"],"962":["FLIGHT"],"963":["EECOM"],"964":["FLIGHT"],"965":["EECOM"],"966":["FLIGHT"],"967":["FLIGHT","TELMU"],"968":["FLIGHT","TELMU"],"969":["FLIGHT"],"970":["TELMU"],"971":["FLIGHT"],"972":["CSM","TELMU"],"973":["CSM","FLIGHT"],"974":["Amps","TELMU"],"975":["FLIGHT"],"976":["TELMU"],"977":["MAIN B","FLIGHT","TELMU"],"978":["TELMU"],"979":["FLIGHT","EECOM","GNC"],"980":["FLIGHT"],"981":["FLIGHT"],"982":["FLIGHT"],"983":["EECOM"],"984":["FLIGHT","EECOM"],"985":["EECOM"],"986":["FLIGHT"],"987":["FLIGHT","EECOM"],"988":["FLIGHT"],"989":["DPS","FLIGHT","CAPCOM"],"990":["FLIGHT","GUIDO"],"991":["FLIGHT"],"992":["GUIDO"],"993":["FLIGHT","EECOM"],"994":["FLIGHT"],"995":["EECOM"],"996":["FLIGHT"],"997":["FLIGHT"],"998":["EECOM"],"999":["FLIGHT"],"1000":["FLIGHT"],"1001":["FLIGHT","EECOM"],"1002":["FLIGHT"],"1003":["EECOM"],"1004":["FLIGHT"],"1005":["EECOM"],"1006":["FLIGHT","CAPCOM"],"1007":["P52","CAPCOM"],"1008":["FLIGHT"],"1009":["FLIGHT","GUIDO"],"1010":["CSM","P52","FLIGHT","CONTROL"],"1011":["FLIGHT","CONTROL"],"1012":["FLIGHT"],"1013":["CONTROL"],"1014":["FLIGHT"],"1015":["GUIDO"],"1016":["FLIGHT","CAPCOM"],"1017":["AOT","CAPCOM"],"1018":["FLIGHT","CONTROL"],"1019":["FLIGHT"],"1020":["FLIGHT"],"1021":["CAPCOM"],"1022":["FLIGHT","EECOM"],"1023":["EECOM"],"1024":["FLIGHT"],"1025":["FLIGHT","EECOM"],"1026":["FLIGHT","EECOM"],"1027":["FLIGHT"],"1028":["FLIGHT","EECOM"],"1029":["FLIGHT"],"1030":["FLIGHT","EECOM"],"1031":["FLIGHT","EECOM","GNC"],"1032":["Attitude","CMC","FLIGHT","GNC"],"1033":["CMC","FLIGHT"],"1034":["FLIGHT","GNC"],"1035":["FLIGHT","EECOM"],"1036":["FLIGHT","EECOM"],"1037":["FLIGHT","EECOM"],"1038":["FLIGHT"],"1039":["EECOM"],"1040":["FLIGHT"],"1041":["EECOM"],"1042":["FLIGHT","CONTROL"],"1043":["GUIDO"],"1044":["FLIGHT","CONTROL"],"1045":["FLIGHT","TELMU","CSM"],"1046":["FLIGHT","TELMU"],"1047":["TELMU"],"1048":["FLIGHT"],"1049":["FLIGHT"],"1050":["FLIGHT","TELMU"],"1051":["FLIGHT"],"1052":["Jets","Quad","FLIGHT","GNC"],"1053":["RCS","FLIGHT"],"1054":["GNC"],"1055":["FLIGHT","EECOM"],"1056":["FLIGHT","EECOM"],"1057":["FLIGHT"],"1058":["FLIGHT","EECOM"],"1059":["FLIGHT"],"1060":["EECOM"],"1061":["FLIGHT"],"1062":["EECOM"],"1063":["INCO"],"1064":["EECOM"],"1065":["EECOM","GNC"],"1066":["RCS","Quad","FLIGHT"],"1067":["EECOM"],"1068":["RCS","Quad","FLIGHT","GNC"],"1069":["FLIGHT","GNC"],"1070":["FLIGHT","GNC"],"1071":["Quad","FLIGHT"],"1072":["O2","FLIGHT","GNC","MAIN B"],"1073":["FLIGHT"],"1074":["FLIGHT"],"1075":["GNC"],"1076":["RCS","Quad","FLIGHT"],"1077":["RCS","CAPCOM"],"1078":["FLIGHT"],"1079":["CAPCOM"],"1080":["FLIGHT","INCO"],"1081":["CAPCOM"],"1082":["FLIGHT","EECOM"],"1083":["FLIGHT","EECOM"],"1084":["MAIN B","FLIGHT"],"1085":["FLIGHT","EECOM"],"1086":["FLIGHT"],"1087":["EECOM"],"1088":["FLIGHT"],"1089":["FLIGHT"],"1090":["Rates","FLIGHT","GNC"],"1091":["FLIGHT","GNC"],"1092":["FLIGHT","EECOM"],"1093":["FLIGHT","EECOM"],"1094":["FLIGHT"],"1095":["EECOM"],"1096":["FLIGHT","TELMU"],"1097":["FLIGHT","TELMU"],"1098":["FLIGHT","EECOM"],"1099":["FLIGHT","EECOM"],"1100":["FLIGHT"],"1101":["EECOM"],"1102":["CSM","FLIGHT","EECOM","TELMU"],"1103":["TELMU"],"1104":["FLIGHT"],"1105":["TELMU"],"1106":["FLIGHT","EECOM"],"1107":["FLIGHT"],"1108":["FLIGHT"],"1109":["EECOM"],"1110":["ECS","FLIGHT","TELMU"],"1111":["EECOM"],"1112":["TM","FLIGHT","CSM"],"1113":["EECOM"],"1114":["EECOM"],"1115":["FLIGHT"],"1116":["FLIGHT"],"1117":["CAPCOM"],"1118":["CSM","FLIGHT"],"1119":["CAPCOM"],"1120":["FLIGHT","GNC"],"1121":["FLIGHT","GNC"],"1122":["MAIN B","GNC"],"1123":["MAIN B","FLIGHT","CAPCOM"],"1124":["FLIGHT","TELMU"],"1125":["FLIGHT","TELMU"],"1126":["FLIGHT"],"1127":["TELMU"],"1128":["FLIGHT"],"1129":["FLIGHT","EECOM"],"1130":["FLIGHT","EECOM"],"1131":["FLIGHT"],"1132":["CSM","EECOM"],"1133":["CSM","FLIGHT","CAPCOM","EECOM"],"1134":["EECOM"],"1135":["CSM","FLIGHT","EECOM","GNC"],"1136":["FLIGHT","EECOM"],"1137":["CMC","FLIGHT","GNC"],"1138":["FLIGHT"],"1139":["FLIGHT","EECOM"],"1140":["FLIGHT"],"1141":["O2","EECOM"],"1142":["EECOM"],"1143":["MAIN A","FLIGHT"],"1144":["EECOM"],"1145":["FLIGHT"],"1146":["EECOM"],"1147":["FLIGHT","CAPCOM"],"1148":["FLIGHT"],"1149":["CAPCOM"],"1150":["FLIGHT","CONTROL","TELMU"],"1151":["CONTROL"],"1152":["FLIGHT","GUIDO"],"1153":["CSM","FLIGHT"],"1154":["FLIGHT","GUIDO"],"1155":["FLIGHT"],"1156":["PTC","GUIDO"],"1157":["FLIGHT"],"1158":["FLIGHT","EECOM"],"1159":["FLIGHT","EECOM"],"1160":["FLIGHT"],"1161":["FLIGHT","EECOM"],"1162":["FLIGHT"],"1163":["CAPCOM"],"1164":["FLIGHT"],"1165":["CSM","FLIGHT","CONTROL","TELMU"],"1166":["AOT","FLIGHT"],"1167":["FLIGHT","GUIDO"],"1168":["FLIGHT","CONTROL"],"1169":["FLIGHT"],"1170":["CONTROL"],"1171":["FLIGHT"],"1172":["GUIDO"],"1173":["CONTROL"],"1174":["CAPCOM"],"1175":["FLIGHT","Coarse Align"],"1176":["GUIDO"],"1177":["FLIGHT","GUIDO"],"1178":["FLIGHT","EECOM"],"1179":["FLIGHT","GUIDO"],"1180":["FLIGHT"],"1181":["CSM","P52","GUIDO"],"1182":["FLIGHT"],"1183":["GUIDO"],"1184":["FLIGHT"],"1185":["FLIGHT","GNC"],"1186":["FLIGHT"],"1187":["FLIGHT","EECOM"],"1188":["FLIGHT","GUIDO"],"1189":["FLIGHT"],"1190":["FLIGHT","EECOM"],"1191":["Surge Tank","EECOM"],"1192":["FLIGHT"],"1193":["FLIGHT","EECOM"],"1194":["FLIGHT","CAPCOM"],"1195":["FLIGHT","TELMU"],"1196":["FLIGHT","TELMU"],"1197":["FLIGHT"],"1198":["TELMU"],"1199":["FLIGHT"],"1200":["FLIGHT","EECOM"],"1201":["FLIGHT"],"1202":["TELMU"],"1203":["FLIGHT"],"1204":["TELMU"],"1205":["TELMU"],"1206":["FLIGHT"],"1207":["TELMU"],"1208":["FLIGHT","ECS"],"1209":["FLIGHT","EECOM"],"1210":["Glycol","TELMU"],"1211":["ECS","FLIGHT"],"1212":["Surge Tank","EECOM"],"1213":["FLIGHT"],"1214":["FLIGHT"],"1215":["TELMU"],"1216":["FLIGHT"],"1217":["TELMU"],"1218":["FLIGHT"],"1219":["TELMU"],"1220":["FLIGHT"],"1221":["TELMU"],"1222":["FLIGHT"],"1223":["FLIGHT","TELMU"],"1224":["FLIGHT"],"1225":["TELMU"],"1226":["FLIGHT"],"1227":["TELMU"],"1228":["FLIGHT"],"1229":["TELMU"],"1230":["FLIGHT","CAPCOM"],"1231":["CAPCOM"],"1232":["FLIGHT","TELMU"],"1233":["FLIGHT"],"1234":["Glycol","ECS","FLIGHT"],"1235":["TELMU"],"1236":["FLIGHT"],"1237":["FLIGHT","TELMU"],"1238":["FLIGHT"],"1239":["TELMU"],"1240":["FLIGHT"],"1241":["FLIGHT","TELMU"],"1242":["TELMU"],"1243":["FLIGHT"],"1244":["FLIGHT"],"1245":["FLIGHT"],"1246":["FLIGHT"],"1247":["FLIGHT"],"1248":["FLIGHT","TELMU"],"1249":["TELMU"],"1250":["FLIGHT"],"1251":["FLIGHT"],"1252":["FLIGHT","EECOM"],"1253":["FLIGHT"],"1254":["EECOM"],"1255":["FLIGHT"],"1256":["CSM","EECOM"],"1257":["FLIGHT"],"1258":["EECOM"],"1259":["CSM","GUIDO"],"1260":["FLIGHT"],"1261":["MAIN A","EECOM"],"1262":["FLIGHT"],"1263":["FLIGHT","EECOM"],"1264":["FLIGHT"],"1265":["GUIDO"],"1266":["FLIGHT"],"1267":["GUIDO"],"1268":["FLIGHT"],"1269":["EECOM"],"1270":["FLIGHT"],"1271":["FLIGHT"],"1272":["Coarse Align","FLIGHT","CONTROL","TELMU"],"1273":["FLIGHT","CONTROL","TELMU"],"1274":["FLIGHT","TELMU"],"1275":["CONTROL"],"1276":["Coarse Align","FLIGHT"],"1277":["TELMU"],"1278":["CONTROL"],"1279":["Coarse Align","FLIGHT"],"1280":["FLIGHT","CONTROL"],"1281":["EECOM"],"1282":["FLIGHT"],"1283":["EECOM"],"1284":["FLIGHT"],"1285":["EECOM"],"1286":["Coarse Align","FLIGHT"],"1287":["EECOM"],"1288":["Coarse Align","FLIGHT"],"1289":["FLIGHT","EECOM"],"1290":["FLIGHT","GUIDO"],"1291":["CSM","FLIGHT","CAPCOM","EECOM"],"1292":["FLIGHT","EECOM"],"1293":["FLIGHT"],"1294":["EECOM"],"1295":["EECOM"],"1296":["CAPCOM"],"1297":["MAIN A","EECOM"],"1298":["FLIGHT"],"1299":["FLIGHT","TELMU"],"1300":["FLIGHT"],"1301":["FLIGHT"],"1302":["FLIGHT","CONTROL","TELMU"],"1303":["CONTROL"],"1304":["Coarse Align","FLIGHT"],"1305":["FLIGHT"],"1306":["FLIGHT","CONTROL"],"1307":["FLIGHT","CAPCOM"],"1308":["CAPCOM"],"1309":["Coarse Align","FLIGHT"],"1310":["CAPCOM"],"1311":["FLIGHT"],"1312":["Fuel cell","CAPCOM"],"1313":["FLIGHT"],"1314":["FLIGHT","EECOM","GNC","INCO"],"1315":["FLIGHT","GNC"],"1316":["INCO"],"1317":["FLIGHT","GNC"],"1318":["FLIGHT","GNC"],"1319":["FLIGHT","EECOM"],"1320":["FLIGHT"],"1321":["CSM","EECOM"],"1322":["FLIGHT"],"1323":["EECOM"],"1324":["FLIGHT"],"1325":["EECOM"],"1326":["FLIGHT","EECOM"],"1327":["FLIGHT"],"1328":["FLIGHT"],"1329":["CAPCOM"],"1330":["FLIGHT"],"1331":["FLIGHT","EECOM"],"1332":["FLIGHT"],"1333":["EECOM"],"1334":["FLIGHT"],"1335":["FLIGHT","EECOM"],"1336":["EECOM"],"1337":["FLIGHT"],"1338":["EECOM"],"1339":["FLIGHT"],"1340":["FLIGHT","EECOM"],"1341":["EECOM"],"1342":["FLIGHT"],"1343":["EECOM"],"1344":["FLIGHT"],"1345":["INCO"],"1346":["FLIGHT"],"1347":["FLIGHT"],"1348":["FLIGHT"],"1349":["FLIGHT","INCO"],"1350":["FLIGHT"],"1351":["PCM","INCO"],"1352":["FLIGHT","CAPCOM"],"1353":["FLIGHT","TELMU"],"1354":["FLIGHT"],"1355":["TELMU"],"1356":["FLIGHT","CONTROL"],"1357":["ECS","TELMU"],"1358":["FLIGHT"],"1359":["TELMU"],"1360":["FLIGHT","CONTROL"],"1361":["FLIGHT","CONTROL"],"1362":["FLIGHT","CAPCOM","CONTROL"],"1363":["DSKY","CONTROL"],"1364":["FLIGHT"],"1365":["CONTROL"],"1366":["FLIGHT"],"1367":["CONTROL"],"1368":["FLIGHT"],"1369":["CONTROL"],"1370":["Coarse Align","FLIGHT"],"1371":["CONTROL"],"1372":["FLIGHT"],"1373":["CONTROL"],"1374":["FLIGHT"],"1375":["Coarse Align","CONTROL"],"1376":["FLIGHT","CAPCOM"],"1377":["FLIGHT","CONTROL"],"1378":["FLIGHT"],"1379":["DSKY","CAPCOM"],"1380":["Glycol","FLIGHT","TELMU"],"1381":["TELMU"],"1382":["FLIGHT"],"1383":["FLIGHT","TELMU"],"1384":["FLIGHT"],"1385":["FLIGHT","EECOM"],"1386":["FLIGHT"],"1387":["Fuel cell","EECOM"],"1388":["Fuel cell","FLIGHT"],"1389":["EECOM"],"1390":["FLIGHT"],"1391":["Fuel cell","FLIGHT"],"1392":["EECOM"],"1393":["FLIGHT"],"1394":["EECOM"],"1395":["FLIGHT"],"1396":["FLIGHT"],"1397":["CAPCOM"],"1398":["FLIGHT"],"1399":["CAPCOM"],"1400":["CAPCOM"],"1401":["FLIGHT"],"1402":["EECOM"],"1403":["FLIGHT","EECOM"],"1404":["FLIGHT","GNC"],"1405":["FLIGHT","GNC"],"1406":["FLIGHT"],"1407":["GNC"],"1408":["FLIGHT","EECOM"],"1409":["FLIGHT"],"1410":["Glycol","EECOM"],"1411":["FLIGHT","EECOM"],"1412":["FLIGHT"],"1413":["EECOM"],"1414":["Glycol","EECOM"],"1415":["CSM","Glycol","FLIGHT","CAPCOM"],"1416":["CAPCOM"],"1417":["EECOM"],"1418":["FLIGHT"],"1419":["EECOM"],"1420":["EECOM"],"1421":["FLIGHT"],"1422":["FLIGHT","TELMU"],"1423":["FLIGHT"],"1424":["TELMU"],"1425":["TM","FLIGHT"],"1426":["TELMU"],"1427":["Glycol","FLIGHT"],"1428":["FLIGHT","CAPCOM"],"1429":["FLIGHT"],"1430":["CAPCOM"],"1431":["CSM","FLIGHT","EECOM"],"1432":["Amps","EECOM"],"1433":["FLIGHT"],"1434":["CAPCOM","EECOM"],"1435":["FLIGHT"],"1436":["EECOM"],"1437":["FLIGHT"],"1438":["FLIGHT","EECOM"],"1439":["FLIGHT"],"1440":["O2","EECOM"],"1441":["FLIGHT"],"1442":["EECOM"],"1443":["O2","FLIGHT","CAPCOM"],"1444":["CAPCOM"],"1445":["O2","FLIGHT"],"1446":["Fuel cell","Fuel Cell Pumps","FLIGHT","EECOM"],"1447":["FLIGHT"],"1448":["EECOM"],"1449":["EECOM"],"1450":["Fuel cell","Fuel Cell Pumps","FLIGHT","CAPCOM"],"1451":["Fuel cell","Fuel Cell Pumps","CAPCOM","O2"],"1452":["FLIGHT"],"1453":["FLIGHT"],"1454":["FLIGHT","INCO"],"1455":["CAPCOM"],"1456":["FLIGHT","EECOM"],"1457":["EECOM"],"1458":["FLIGHT","CAPCOM"],"1459":["EECOM"],"1460":["CAPCOM"],"1461":["CMC","Amps","FLIGHT","EECOM"],"1462":["FLIGHT","EECOM"],"1463":["FLIGHT"],"1464":["CMC","EECOM"],"1465":["FLIGHT"],"1466":["FLIGHT","EECOM"],"1467":["FLIGHT","EECOM"],"1468":["FLIGHT"],"1469":["EECOM"],"1470":["FLIGHT"],"1471":["EECOM"],"1472":["FLIGHT","GNC"],"1473":["FLIGHT","GNC"],"1474":["FLIGHT"],"1475":["GNC"],"1476":["Amps","FLIGHT"],"1477":["GNC"],"1478":["Amps","FLIGHT"],"1479":["GNC"],"1480":["FLIGHT"],"1481":["GNC"],"1482":["FLIGHT"],"1483":["GNC"],"1484":["FLIGHT","CAPCOM"],"1485":["FLIGHT"],"1486":["CAPCOM"],"1487":["FLIGHT","INCO"],"1488":["FLIGHT","INCO"],"1489":["FLIGHT"],"1490":["210","INCO"],"1491":["210","FLIGHT","NETWORK"],"1492":["FLIGHT"],"1493":["FLIGHT","NETWORK"],"1494":["FLIGHT"],"1495":["FLIGHT","GNC"],"1496":["FLIGHT"],"1497":["Amps","GNC"],"1498":["FLIGHT","CONTROL"],"1499":["FLIGHT"],"1500":["CONTROL"],"1501":["Amps","FLIGHT","GNC"],"1502":["FLIGHT","GNC"],"1503":["FLIGHT"],"1504":["FLIGHT"],"1505":["FLIGHT","GNC"],"1506":["FLIGHT","EECOM"],"1507":["FLIGHT","EECOM"],"1508":["FLIGHT","EECOM"],"1509":["Amps","FLIGHT"],"1510":["EECOM"],"1511":["FLIGHT"],"1512":["FLIGHT","GUIDO"],"1513":["CSM","EECOM"],"1514":["Amps","FLIGHT","EECOM"],"1515":["FLIGHT","TELMU"],"1516":["FLIGHT","TELMU"],"1517":["FLIGHT","TELMU"],"1518":["FLIGHT"],"1519":["CAPCOM"],"1520":["TELMU"],"1521":["FLIGHT","CAPCOM"],"1522":["CAPCOM"],"1523":["FLIGHT","TELMU"],"1524":["FLIGHT"],"1525":["FLIGHT","INCO"],"1526":["FLIGHT"],"1527":["INCO"],"1528":["FLIGHT"],"1529":["INCO"],"1530":["FLIGHT"],"1531":["FLIGHT","CONTROL"],"1532":["FLIGHT"],"1533":["CONTROL"],"1534":["FLIGHT"],"1535":["FLIGHT","TELMU"],"1536":["FLIGHT"],"1537":["TELMU"],"1538":["FLIGHT","CAPCOM"],"1539":["Coarse Align","FLIGHT","CONTROL"],"1540":["CONTROL"],"1541":["FLIGHT","GUIDO"],"1542":["CONTROL"],"1543":["FLIGHT"],"1544":["FLIGHT","GUIDO"],"1545":["FLIGHT"],"1546":["CSM","GUIDO"],"1547":["FLIGHT"],"1548":["GUIDO"],"1549":["CAPCOM"],"1550":["GUIDO"],"1551":["CAPCOM"],"1552":["FLIGHT"],"1553":["GUIDO"],"1554":["FLIGHT","EECOM"],"1555":["FLIGHT"],"1556":["EECOM"],"1557":["FLIGHT"],"1558":["FLIGHT","EECOM"],"1559":["FLIGHT","EECOM"],"1560":["FLIGHT"],"1561":["EECOM"],"1562":["FLIGHT"],"1563":["FLIGHT"],"1564":["EECOM"],"1565":["FLIGHT","GNC"],"1566":["FLIGHT","GNC"],"1567":["FLIGHT"],"1568":["GNC"],"1569":["FLIGHT","CONTROL"],"1570":["FLIGHT"],"1571":["CONTROL"],"1572":["FLIGHT"],"1573":["FLIGHT"],"1574":["CONTROL"],"1575":["FLIGHT","CONTROL"],"1576":["CONTROL"],"1577":["CAPCOM"],"1578":["FLIGHT","EECOM"],"1579":["FLIGHT","EECOM"],"1580":["FLIGHT"],"1581":["EECOM"],"1582":["FLIGHT","CAPCOM"],"1583":["CAPCOM"],"1584":["FLIGHT","EECOM"],"1585":["FLIGHT"],"1586":["O2","EECOM"],"1587":["FLIGHT","CAPCOM"],"1588":["FLIGHT"],"1589":["FLIGHT"],"1590":["FLIGHT"],"1591":["FLIGHT"],"1592":["FLIGHT","GUIDO"],"1593":["Amps","FLIGHT","EECOM"],"1594":["FLIGHT","EECOM"],"1595":["FLIGHT"],"1596":["FLIGHT","GUIDO"],"1597":["CSM","FLIGHT"],"1598":["FLIGHT","GUIDO"],"1599":["FLIGHT"],"1600":["GUIDO"],"1601":["FLIGHT","INCO"],"1602":["FLIGHT"],"1603":["INCO"],"1604":["FLIGHT"],"1605":["PCM","INCO"],"1606":["FLIGHT","CAPCOM"],"1607":["EECOM","INCO"],"1608":["CAPCOM"],"1609":["FLIGHT"],"1610":["FLIGHT","CAPCOM"],"1611":["FLIGHT"],"1612":["FLIGHT","GUIDO"],"1613":["FLIGHT"],"1614":["GUIDO"],"1615":["FLIGHT","EECOM"],"1616":["FLIGHT"],"1617":["EECOM"],"1618":["FLIGHT","INCO"],"1619":["INCO"],"1620":["CSM","FLIGHT"],"1621":["INCO"],"1622":["FLIGHT"],"1623":["INCO"],"1624":["CSM","FLIGHT","CAPCOM"],"1625":["CAPCOM"],"1626":["EECOM","INCO"],"1627":["FLIGHT","TELMU"],"1628":["FLIGHT"],"1629":["TELMU"],"1630":["FLIGHT"],"1631":["FLIGHT","CAPCOM"],"1632":["FLIGHT"],"1633":["FLIGHT","GUIDO"],"1634":["FLIGHT"],"1635":["GUIDO"],"1636":["FLIGHT","CAPCOM"],"1637":["FLIGHT","TELMU"],"1638":["Coarse Align","GUIDO"],"1639":["Coarse Align","FLIGHT","TELMU"],"1640":["FLIGHT","CAPCOM"],"1641":["FLIGHT"],"1642":["CMC","FLIGHT"],"1643":["CAPCOM"],"1644":["FLIGHT","INCO"],"1645":["CSM","INCO"],"1646":["FLIGHT"],"1647":["INCO"],"1648":["FLIGHT"],"1649":["INCO"],"1650":["FLIGHT"],"1651":["Fine Align","FLIGHT"],"1652":["CSM","FLIGHT","GUIDO"],"1653":["FLIGHT"],"1654":["GUIDO"],"1655":["CSM","FLIGHT","CAPCOM"],"1656":["FLIGHT"],"1657":["FLIGHT","GUIDO"],"1658":["FLIGHT"],"1659":["FLIGHT"],"1660":["FLIGHT","EECOM"],"1661":["FLIGHT"],"1662":["CMC","EECOM"],"1663":["FLIGHT"],"1664":["EECOM"],"1665":["FLIGHT"],"1666":["FLIGHT","GUIDO"],"1667":["FLIGHT","GUIDO"],"1668":["CMC","FLIGHT"],"1669":["FLIGHT","GUIDO"],"1670":["FLIGHT"],"1671":["GUIDO"],"1672":["FLIGHT"],"1673":["FLIGHT","INCO"],"1674":["FLIGHT"],"1675":["INCO"],"1676":["CSM","FLIGHT"],"1677":["INCO"],"1678":["FLIGHT"],"1679":["CSM","Fine Align","FLIGHT","CONTROL"],"1680":["FLIGHT","GUIDO"],"1681":["FLIGHT","CONTROL"],"1682":["CSM","FLIGHT"],"1683":["CONTROL"],"1684":["CMC","CSM","Fine Align","FLIGHT","CAPCOM"],"1685":["FLIGHT","GNC"],"1686":["FLIGHT","EECOM"],"1687":["GNC"],"1688":["FLIGHT"],"1689":["GNC"],"1690":["FLIGHT"],"1691":["GNC"],"1692":["FLIGHT"],"1693":["GNC"],"1694":["FLIGHT","EECOM"],"1695":["CSM","FLIGHT","CAPCOM"],"1696":["CMC","CAPCOM"],"1697":["FLIGHT"],"1698":["CAPCOM"],"1699":["FLIGHT"],"1700":["EECOM"],"1701":["FLIGHT"],"1702":["CAPCOM"],"1703":["FLIGHT"],"1704":["FLIGHT","TELMU"],"1705":["FLIGHT"],"1706":["Glycol","TELMU"],"1707":["FLIGHT"],"1708":["TELMU"],"1709":["FLIGHT","EECOM"],"1710":["FLIGHT","EECOM"],"1711":["FLIGHT"],"1712":["EECOM"],"1713":["FLIGHT","EECOM"],"1714":["FLIGHT"],"1715":["RCS","EECOM"],"1716":["FLIGHT","CAPCOM"],"1718":["FLIGHT"],"1719":["CSM","FLIGHT","CAPCOM"],"1720":["FLIGHT","CONTROL"],"1721":["FLIGHT"],"1722":["RCS","CONTROL"],"1723":["FLIGHT"],"1724":["CONTROL"],"1725":["FLIGHT"],"1726":["CSM","FLIGHT"],"1727":["FLIGHT","EECOM"],"1728":["FLIGHT"],"1729":["O2","EECOM"],"1730":["FLIGHT","CAPCOM"],"1731":["FLIGHT","EECOM"],"1732":["FLIGHT"],"1733":["FLIGHT","EECOM"],"1734":["FLIGHT"],"1735":["FLIGHT"],"1736":["RCS","FLIGHT"],"1737":["FLIGHT","EECOM"],"1738":["FLIGHT"],"1739":["EECOM"],"1740":["FLIGHT","CAPCOM"],"1741":["FLIGHT","TELMU"],"1742":["FLIGHT"],"1743":["Glycol","TELMU"],"1744":["FLIGHT"],"1745":["TELMU"],"1746":["FLIGHT"],"1747":["Glycol","TELMU"],"1748":["FLIGHT"],"1749":["TELMU"],"1750":["FLIGHT"],"1751":["TELMU"],"1752":["FLIGHT"],"1753":["Amps","FLIGHT"],"1754":["FLIGHT","CAPCOM"],"1755":["FLIGHT"],"1756":["FLIGHT","EECOM"],"1757":["FLIGHT","EECOM"],"1758":["O2","EECOM"],"1759":["O2","FLIGHT"],"1760":["O2","CAPCOM"],"1761":["FLIGHT"],"1762":["CAPCOM"],"1763":["FLIGHT"],"1764":["FLIGHT","CONTROL"],"1765":["FLIGHT"],"1766":["RCS","CONTROL"],"1767":["CSM","RCS","GNC"],"1768":["FLIGHT"],"1769":["GNC"],"1770":["FLIGHT"],"1771":["TELMU"],"1772":["FLIGHT","CAPCOM"],"1773":["O2","EECOM"],"1774":["O2","FLIGHT"],"1775":["FLIGHT"],"1776":["FLIGHT","EECOM"],"1777":["CSM","FLIGHT"],"1778":["RCS","FLIGHT","CAPCOM"],"1779":["CAPCOM","RCS"],"1780":["FLIGHT"],"1781":["RCS","FLIGHT"],"1782":["CSM","CAPCOM"],"1783":["FLIGHT"],"1784":["RCS","FLIGHT","CONTROL"],"1785":["RCS","FLIGHT","CONTROL"],"1786":["FLIGHT"],"1787":["CONTROL"],"1788":["RCS","FLIGHT","CAPCOM"],"1789":["FLIGHT","CONTROL"],"1790":["FLIGHT"],"1791":["FLIGHT","CAPCOM"],"1792":["CSM","FLIGHT"],"1793":["FLIGHT","EECOM"],"1794":["FLIGHT"],"1795":["EECOM"],"1796":["FLIGHT","GUIDO"],"1797":["CSM","Jets","FLIGHT","GNC"],"1798":["FLIGHT","GNC"],"1799":["RCS","FLIGHT","CAPCOM"],"1800":["Quad","CONTROL"],"1801":["CAPCOM"],"1802":["CONTROL"],"1803":["FLIGHT","EECOM","GNC"],"1804":["FLIGHT","EECOM"],"1805":["SCS","FLIGHT"],"1806":["RCS","FLIGHT","CONTROL"],"1807":["FLIGHT","CONTROL"],"1808":["FLIGHT"],"1809":["CONTROL"],"1810":["FLIGHT","CAPCOM"],"1811":["CONTROL"],"1812":["CMC","FLIGHT","GNC"],"1813":["FLIGHT"],"1814":["FLIGHT","CONTROL"],"1815":["FLIGHT","CONTROL"],"1816":["FLIGHT"],"1817":["FLIGHT"],"1818":["FLIGHT","CONTROL"],"1819":["FLIGHT","CONTROL"],"1820":["FLIGHT","CONTROL"],"1821":["FLIGHT"],"1822":["Attitude","PGNCS","CONTROL"],"1823":["FLIGHT"],"1824":["FLIGHT","CAPCOM"],"1825":["CONTROL","FLIGHT"],"1826":["FLIGHT"],"1827":["FLIGHT"],"1828":["FLIGHT","EECOM"],"1829":["CSM","FLIGHT","GNC"],"1830":["FLIGHT","GNC"],"1831":["CSM","FLIGHT"],"1832":["FLIGHT","GNC"],"1833":["FLIGHT","GNC"],"1834":["FLIGHT","GUIDO"],"1835":["CSM","FLIGHT"],"1836":["GUIDO"],"1837":["Attitude","FLIGHT"],"1838":["FLIGHT","CAPCOM"],"1839":["FLIGHT"],"1840":["Attitude","CAPCOM"],"1841":["Attitude","CSM","FLIGHT"],"1842":["FLIGHT","CONTROL"],"1843":["FLIGHT"],"1844":["CONTROL"],"1845":["FLIGHT"],"1846":["Attitude","FLIGHT"],"1847":["PGNCS","CONTROL"],"1848":["FLIGHT"],"1849":["FLIGHT"],"1850":["Attitude","FLIGHT","CAPCOM"],"1851":["FLIGHT"],"1852":["GUIDO"],"1853":["FLIGHT"],"1854":["FLIGHT","CONTROL"],"1855":["FLIGHT"],"1856":["Gimbal lock","RCS","CONTROL"],"1857":["FLIGHT"],"1858":["FLIGHT"],"1859":["DSKY","FLIGHT","CONTROL"],"1860":["CSM","FLIGHT"],"1861":["GUIDO"],"1862":["FLIGHT","GNC"],"1863":["FLIGHT","CAPCOM","GNC"],"1864":["FLIGHT"],"1865":["DIRECT","RCS","FLIGHT","GUIDO"],"1866":["Attitude","CSM","DIRECT","RCS","FLIGHT","CAPCOM"],"1867":["FLIGHT","TELMU"],"1868":["FLIGHT"],"1869":["TELMU"],"1870":["FLIGHT"],"1871":["TELMU"],"1872":["FLIGHT","CAPCOM"],"1873":["FLIGHT","TELMU"],"1874":["FLIGHT","TELMU"],"1875":["TELMU"],"1876":["FLIGHT"],"1877":["RCS","CONTROL"],"1878":["FLIGHT"],"1879":["FLIGHT","TELMU"],"1880":["FLIGHT","CAPCOM"],"1881":["FLIGHT","TELMU"],"1882":["FLIGHT","TELMU"],"1883":["Current","FLIGHT"],"1884":["Amps","TELMU"],"1885":["FLIGHT","TELMU"],"1886":["FLIGHT","TELMU"],"1887":["FLIGHT"],"1888":["TELMU"],"1889":["FLIGHT"],"1890":["FLIGHT","TELMU"],"1891":["FLIGHT"],"1892":["FLIGHT","TELMU"],"1893":["FLIGHT"],"1894":["FLIGHT","CONTROL","TELMU"],"1895":["CONTROL"],"1896":["FLIGHT"],"1897":["FLIGHT","CONTROL"],"1898":["CAPCOM"],"1899":["CONTROL"],"1900":["FLIGHT"],"1901":["CONTROL"],"1902":["FLIGHT"],"1903":["Attitude","PGNCS","CONTROL"],"1904":["FLIGHT"],"1905":["CONTROL"],"1906":["FLIGHT"],"1907":["FLIGHT","CONTROL"],"1908":["Attitude","PGNCS","FLIGHT"],"1909":["FLIGHT","CONTROL"],"1910":["FLIGHT"],"1911":["CONTROL"],"1912":["FLIGHT"],"1913":["CONTROL"],"1914":["FLIGHT"],"1915":["FLIGHT"],"1916":["CAPCOM"],"1917":["CSM","CONTROL"],"1918":["FLIGHT"],"1919":["CSM","CONTROL"],"1920":["CSM","FLIGHT"],"1921":["Attitude","PGNCS","CAPCOM"],"1922":["FLIGHT","CONTROL"],"1923":["FLIGHT","CONTROL"],"1924":["Attitude","PGNCS","FLIGHT"],"1925":["Attitude","P00","FLIGHT","CONTROL"],"1926":["CAPCOM"],"1927":["FLIGHT"],"1928":["FLIGHT"],"1929":["FLIGHT","CONTROL"],"1930":["FLIGHT"],"1931":["Jets","CONTROL"],"1932":["FLIGHT"],"1933":["FLIGHT"],"1934":["CONTROL"],"1935":["CAPCOM"],"1936":["FLIGHT"],"1937":["CONTROL"],"1938":["CAPCOM"],"1939":["Attitude","DIRECT","CONTROL"],"1940":["FLIGHT"],"1941":["CONTROL"],"1942":["Attitude","CAPCOM"],"1943":["CSM","FLIGHT"],"1944":["FLIGHT"],"1945":["CAPCOM"],"1946":["FLIGHT","CONTROL"],"1947":["CONTROL"],"1948":["FLIGHT"],"1949":["DSKY","Jets","CONTROL"],"1950":["FLIGHT","TELMU"],"1951":["FLIGHT","TELMU"],"1952":["FLIGHT"],"1953":["TELMU"],"1954":["FLIGHT"],"1955":["FLIGHT","GUIDO"],"1956":["FLIGHT","EECOM","GNC"],"1957":["FLIGHT","GNC"],"1958":["EECOM"],"1959":["Attitude","CSM","FLIGHT","CAPCOM"],"1960":["FLIGHT"],"1961":["FLIGHT","EECOM"],"1962":["FLIGHT","EECOM"],"1963":["FLIGHT"],"1964":["FLIGHT","EECOM"],"1965":["FLIGHT"],"1966":["FLIGHT","TELMU"],"1967":["FLIGHT","TELMU"],"1968":["Fuel cell","Open-circuit","CAPCOM"],"1969":["EECOM"],"1970":["FLIGHT","TELMU"],"1971":["FLIGHT","CAPCOM"],"1972":["FLIGHT","CAPCOM"],"1973":["FLIGHT"],"1974":["CAPCOM"],"1975":["FLIGHT","EECOM"],"1976":["FLIGHT"],"1977":["FLIGHT","NETWORK"],"1978":["FLIGHT"],"1979":["NETWORK"],"1980":["FLIGHT"],"1981":["FLIGHT"],"1982":["FLIGHT","TELMU"],"1983":["FLIGHT","TELMU"],"1984":["FLIGHT"],"1985":["TELMU"],"1986":["FLIGHT"],"1987":["FLIGHT"],"1988":["FLIGHT","TELMU"],"1989":["FLIGHT","EECOM"],"1990":["Inverter","FLIGHT","EECOM"],"1991":["FLIGHT"],"1992":["FLIGHT","CAPCOM"],"1993":["FLIGHT"],"1994":["FLIGHT","EECOM","TELMU"],"1995":["FLIGHT","TELMU"],"1996":["NETWORK"],"1997":["FLIGHT"],"1998":["FLIGHT","INCO"],"1999":["FLIGHT"],"2000":["CSM","FLIGHT","INCO"],"2001":["CSM","INCO"],"2002":["FLIGHT","FDO"],"2003":["FLIGHT","FDO"],"2004":["FLIGHT"],"2005":["FLIGHT","FDO"],"2006":["FLIGHT"],"2007":["INCO"],"2008":["FLIGHT"],"2009":["FLIGHT","INCO"],"2010":["FLIGHT"],"2011":["FLIGHT"],"2012":["Amps","CSM","FLIGHT"],"2013":["FLIGHT"],"2014":["FLIGHT"],"2015":["FLIGHT"],"2016":["FLIGHT","CAPCOM"],"2017":["FLIGHT"],"2018":["CAPCOM"],"2019":["FLIGHT"],"2020":["FLIGHT","GUIDO"],"2021":["FLIGHT"],"2022":["Fine Align","GUIDO"],"2023":["FLIGHT","CAPCOM"],"2024":["CAPCOM"],"2025":["FLIGHT","CONTROL","TELMU"],"2026":["FLIGHT","CONTROL"],"2027":["FLIGHT"],"2028":["FLIGHT","CONTROL"],"2029":["FLIGHT"],"2030":["CAPCOM"],"2031":["FLIGHT","CONTROL"],"2032":["CONTROL"],"2033":["FLIGHT","TELMU"],"2034":["FLIGHT","CONTROL"],"2035":["FLIGHT"],"2036":["Fine Align","FLIGHT","CAPCOM"],"2037":["FLIGHT"],"2038":["FLIGHT","GUIDO"],"2039":["FLIGHT"],"2040":["FLIGHT","TELMU"],"2041":["FLIGHT","TELMU"],"2042":["FLIGHT"],"2043":["TELMU"],"2044":["FLIGHT"],"2045":["FLIGHT"],"2046":["TELMU"],"2047":["CAPCOM"],"2048":["FLIGHT"],"2049":["TELMU"],"2050":["CAPCOM"],"2051":["CAPCOM"],"2052":["FLIGHT","TELMU"],"2053":["FLIGHT","TELMU"],"2054":["Current","FLIGHT"],"2055":["TELMU"],"2056":["FLIGHT","CONTROL"],"2057":["FLIGHT","CONTROL"],"2058":["FLIGHT"],"2059":["CONTROL"],"2060":["FLIGHT"],"2061":["FLIGHT","CAPCOM"],"2062":["FLIGHT","CAPCOM"],"2063":["FLIGHT"],"2064":["CAPCOM"],"2065":["FLIGHT"],"2066":["FLIGHT"],"2067":["FLIGHT"],"2068":["FLIGHT"],"2069":["FLIGHT","GUIDO"],"2070":["FLIGHT"],"2071":["FLIGHT","GUIDO"],"2072":["FLIGHT"],"2073":["GUIDO"],"2074":["FLIGHT"],"2075":["FLIGHT","TELMU"],"2076":["FLIGHT"],"2077":["O2","TELMU"],"2078":["FLIGHT"],"2079":["GUIDO"],"2080":["FLIGHT"],"2081":["TELMU"],"2082":["FLIGHT"],"2083":["TELMU"],"2084":["FLIGHT"],"2085":["TELMU"],"2086":["FLIGHT"],"2087":["TELMU"],"2088":["FLIGHT"],"2089":["O2","TELMU"],"2090":["O2","FLIGHT"],"2091":["TELMU"],"2092":["FLIGHT"],"2093":["TELMU"],"2094":["FLIGHT"],"2095":["TELMU"],"2096":["FLIGHT"],"2097":["CAPCOM"],"2098":["FLIGHT"],"2099":["CAPCOM"],"2100":["FLIGHT"],"2101":["O2","CAPCOM"],"2102":["O2","FLIGHT"],"2103":["CAPCOM"],"2104":["FLIGHT","TELMU"],"2105":["FLIGHT","TELMU"],"2106":["O2","FLIGHT"],"2107":["TELMU"],"2108":["FLIGHT","TELMU"],"2109":["FLIGHT"],"2110":["FLIGHT"],"2111":["FLIGHT","CONTROL"],"2112":["FLIGHT"],"2113":["Gimbal lock","CONTROL"],"2114":["Attitude","CONTROL"],"2115":["FLIGHT"],"2116":["ACA","CONTROL"],"2117":["FLIGHT"],"2118":["FLIGHT"],"2119":["CONTROL"],"2120":["FLIGHT"],"2121":["CONTROL"],"2122":["FLIGHT"],"2123":["CONTROL"],"2124":["FLIGHT","CONTROL"],"2125":["FLIGHT"],"2126":["CONTROL"],"2127":["Amps","FLIGHT"],"2128":["FLIGHT"],"2129":["FLIGHT","CONTROL"],"2130":["RCS","CONTROL"],"2131":["FLIGHT"],"2132":["CONTROL"],"2133":["FLIGHT"],"2134":["CONTROL"],"2135":["FLIGHT"],"2136":["FLIGHT","CAPCOM"],"2137":["FLIGHT"],"2138":["FLIGHT"],"2139":["CSM","FLIGHT"],"2141":["FLIGHT"],"2142":["FLIGHT","CAPCOM"],"2143":["FLIGHT"],"2144":["Pitch","Roll","CAPCOM"],"2145":["FLIGHT","RETRO"],"2146":["FLIGHT","RETRO"],"2147":["FLIGHT"],"2148":["FLIGHT","RETRO"],"2149":["DPS","FLIGHT"],"2150":["RETRO"],"2151":["FLIGHT"],"2152":["FLIGHT"],"2153":["RETRO"],"2154":["FLIGHT"],"2155":["FLIGHT","CONTROL"],"2156":["FLIGHT"],"2157":["CONTROL"],"2158":["CAPCOM"],"2159":["FLIGHT","GUIDO"],"2160":["FLIGHT","CAPCOM"],"2161":["CAPCOM"],"2162":["DPS","CAPCOM"],"2163":["FLIGHT"],"2164":["CAPCOM"],"2165":["FLIGHT"],"2166":["CAPCOM"],"2167":["FLIGHT"],"2168":["CAPCOM"],"2169":["FLIGHT"],"2170":["CAPCOM"],"2171":["FLIGHT"],"2172":["FLIGHT","GUIDO"],"2173":["FLIGHT"],"2174":["GUIDO"],"2175":["FLIGHT","CAPCOM"],"2176":["CAPCOM"],"2177":["FLIGHT"],"2178":["FLIGHT"],"2179":["FLIGHT","CAPCOM"],"2180":["FLIGHT","CAPCOM","TELMU"],"2181":["CAPCOM"],"2182":["FLIGHT","CONTROL"],"2183":["FLIGHT","CONTROL"],"2184":["PTC","FLIGHT"],"2185":["FLIGHT","CONTROL"],"2186":["FLIGHT"],"2187":["FLIGHT"],"2188":["CAPCOM"],"2189":["FLIGHT","TELMU"],"2190":["FLIGHT"],"2191":["CAPCOM","TELMU"],"2192":["Fine Align","FLIGHT","CONTROL","RETRO","TELMU"],"2193":["FLIGHT","RETRO"],"2194":["FLIGHT","RETRO"],"2195":["FLIGHT"],"2196":["FDO","RETRO"],"2197":["FLIGHT"],"2198":["RETRO"],"2199":["GUIDO","RETRO"],"2200":["FLIGHT"],"2201":["FLIGHT"],"2202":["FLIGHT","GUIDO"],"2203":["FLIGHT","CAPCOM"],"2204":["FLIGHT","GUIDO"],"2205":["FLIGHT"],"2206":["FLIGHT","GUIDO"],"2207":["FLIGHT"],"2208":["FLIGHT","TELMU"],"2209":["CAPCOM","TELMU"],"2210":["FLIGHT"],"2211":["TELMU"],"2212":["FLIGHT"],"2213":["TELMU"],"2214":["FLIGHT"],"2215":["FLIGHT","GUIDO"],"2216":["FLIGHT"],"2217":["GUIDO"],"2218":["FLIGHT"],"2219":["FLIGHT","CONTROL"],"2220":["FLIGHT"],"2221":["CONTROL"],"2222":["FLIGHT"],"2223":["CONTROL"],"2224":["FLIGHT"],"2225":["FLIGHT"],"2226":["FLIGHT"],"2227":["FLIGHT","GUIDO","INCO"],"2228":["FLIGHT","INCO"],"2229":["INCO"],"2230":["FLIGHT"],"2231":["INCO"],"2232":["FLIGHT"],"2233":["FLIGHT","GUIDO"],"2234":["FLIGHT"],"2235":["FLIGHT","CONTROL"],"2236":["FLIGHT"],"2237":["CONTROL"],"2238":["FLIGHT"],"2239":["FLIGHT","CAPCOM"],"2240":["DSKY","FLIGHT"],"2241":["FLIGHT"],"2242":["FLIGHT"],"2244":["FLIGHT"],"2245":["FLIGHT"],"2246":["FLIGHT","CAPCOM"],"2247":["CAPCOM"],"2248":["FLIGHT"],"2249":["CAPCOM"],"2250":["FLIGHT"],"2251":["CAPCOM"],"2252":["FLIGHT"],"2253":["FLIGHT"],"2254":["FLIGHT"],"2256":["FLIGHT"],"2257":["FLIGHT","GUIDO"],"2258":["FLIGHT"],"2259":["FLIGHT"],"2260":["FLIGHT","INCO"],"2261":["FLIGHT"],"2262":["INCO"],"2263":["FLIGHT","CAPCOM"],"2264":["FLIGHT","GUIDO"],"2265":["FLIGHT","INCO"],"2266":["FLIGHT","INCO"],"2267":["INCO"],"2268":["FLIGHT"],"2269":["INCO"],"2270":["FLIGHT","CAPCOM"],"2271":["INCO"],"2272":["FLIGHT","CAPCOM"],"2273":["FLIGHT","INCO"],"2274":["FLIGHT"],"2275":["CAPCOM"],"2276":["DSKY","FLIGHT"],"2277":["FLIGHT","RETRO"],"2278":["RETRO"],"2279":["FLIGHT"],"2280":["FLIGHT","CONTROL"],"2281":["FLIGHT"],"2282":["CONTROL"],"2283":["FLIGHT"],"2284":["FLIGHT","RETRO"],"2285":["FLIGHT"],"2286":["FLIGHT","INCO"],"2287":["FLIGHT"],"2288":["INCO"],"2289":["FLIGHT"],"2290":["INCO"],"2291":["FLIGHT"],"2292":["FLIGHT","GUIDO"],"2293":["FLIGHT"],"2294":["DSKY","GUIDO"],"2295":["FLIGHT","CAPCOM"],"2296":["FLIGHT","GUIDO"],"2297":["FLIGHT"],"2298":["FLIGHT","CONTROL"],"2299":["CONTROL"],"2300":["FLIGHT"],"2301":["CONTROL"],"2302":["CAPCOM"],"2303":["RCS","FLIGHT"],"2304":["FLIGHT","CONTROL"],"2305":["FLIGHT"],"2306":["CONTROL","Attitude"],"2307":["CAPCOM"],"2308":["FLIGHT"],"2309":["FLIGHT"],"2310":["CONTROL"],"2311":["FLIGHT"],"2312":["CONTROL"],"2313":["P52","FLIGHT"],"2314":["FLIGHT","CONTROL"],"2315":["FLIGHT"],"2316":["CONTROL"],"2317":["FLIGHT"],"2318":["CONTROL"],"2319":["FLIGHT"],"2320":["FLIGHT"],"2321":["CONTROL"],"2322":["FLIGHT"],"2323":["FLIGHT"],"2325":["FLIGHT"],"2326":["FLIGHT","CONTROL"],"2327":["FLIGHT","CONTROL"],"2328":["FLIGHT","CONTROL"],"2329":["FLIGHT"],"2330":["CONTROL"],"2331":["FLIGHT"],"2332":["CONTROL"],"2333":["FLIGHT","GUIDO"],"2334":["FLIGHT"],"2335":["FLIGHT","GUIDO"],"2336":["FLIGHT","CAPCOM"],"2337":["GUIDO"],"2338":["FLIGHT"],"2339":["FLIGHT"],"2340":["FLIGHT"],"2341":["FLIGHT"],"2342":["FLIGHT"],"2343":["FLIGHT","GUIDO"],"2344":["FLIGHT"],"2345":["P00","FLIGHT","GUIDO"],"2346":["FLIGHT"],"2347":["GUIDO"],"2348":["FLIGHT"],"2349":["GUIDO"],"2350":["FLIGHT"],"2351":["GUIDO"],"2352":["FLIGHT","CAPCOM"],"2353":["FLIGHT","GUIDO"],"2354":["FLIGHT"],"2355":["FLIGHT","GUIDO"],"2356":["FLIGHT"],"2357":["GUIDO"],"2358":["FLIGHT"],"2359":["GUIDO"],"2360":["FLIGHT"],"2361":["FLIGHT","GUIDO","PTC"],"2362":["FLIGHT"],"2363":["FLIGHT"],"2364":["FLIGHT"],"2365":["FLIGHT","GUIDO"],"2366":["P00","CAPCOM"],"2367":["GUIDO"],"2368":["FLIGHT"],"2369":["FLIGHT","GUIDO"],"2370":["FLIGHT","INCO"],"2371":["FLIGHT"],"2372":["INCO"],"2373":["FLIGHT"],"2374":["FLIGHT","GUIDO"],"2375":["P00","GUIDO"],"2376":["FLIGHT"],"2377":["INCO"],"2378":["GUIDO"],"2379":["FLIGHT","CAPCOM"],"2380":["FLIGHT","CAPCOM"],"2381":["FLIGHT"],"2382":["FLIGHT"],"2383":["FLIGHT","INCO"],"2384":["FLIGHT"],"2385":["FLIGHT"],"2386":["FLIGHT","INCO"],"2387":["FLIGHT"],"2388":["FLIGHT","GUIDO"],"2389":["FLIGHT","CONTROL"],"2390":["FLIGHT","CONTROL"],"2391":["FLIGHT"],"2392":["TM","FLIGHT","CONTROL"],"2393":["FLIGHT"],"2394":["FLIGHT","CONTROL"],"2395":["FLIGHT"],"2396":["PTC","FLIGHT","CONTROL"],"2397":["FLIGHT","CONTROL"],"2398":["FLIGHT"],"2399":["FLIGHT","INCO"],"2400":["FLIGHT"],"2401":["INCO"],"2402":["FLIGHT"],"2403":["INCO"],"2404":["INCO"],"2405":["FLIGHT","GUIDO"],"2406":["FLIGHT"],"2407":["GUIDO"],"2408":["FLIGHT","CAPCOM"],"2409":["FLIGHT","TELMU"],"2410":["FLIGHT"],"2411":["TELMU"],"2412":["FLIGHT","CAPCOM"],"2413":["FLIGHT","TELMU"],"2414":["FLIGHT"],"2415":["Inverter","TELMU"],"2416":["Inverter","FLIGHT"],"2417":["Inverter","TELMU"],"2418":["FLIGHT"],"2419":["TELMU"],"2420":["FLIGHT"],"2421":["TELMU"],"2422":["Amps","FLIGHT"],"2423":["Amps","TELMU"],"2424":["FLIGHT"],"2425":["TELMU"],"2426":["FLIGHT"],"2427":["TELMU"],"2428":["FLIGHT"],"2429":["Current","TELMU"],"2430":["FLIGHT"],"2431":["TELMU"],"2432":["FLIGHT"],"2433":["TELMU"],"2434":["FLIGHT","CAPCOM","CONTROL","EECOM","GNC","INCO","RETRO","TELMU"],"2435":["FLIGHT","RETRO"],"2436":["FLIGHT","RETRO"],"2437":["GUIDO"],"2438":["Attitude","PTC","FLIGHT","CONTROL"],"2439":["CONTROL"],"2440":["FLIGHT"],"2441":["FLIGHT","CONTROL"],"2442":["FLIGHT"],"2443":["CONTROL"],"2444":["O2","FLIGHT","CONTROL","TELMU"],"2445":["TELMU"],"2446":["Amps","FLIGHT"],"2447":["FLIGHT","TELMU"],"2448":["Amps","FLIGHT"],"2449":["Amps","FLIGHT"],"2450":["FLIGHT","TELMU"],"2451":["FLIGHT"],"2452":["Amps","TELMU"],"2453":["FLIGHT"],"2454":["TELMU"],"2455":["FLIGHT"],"2456":["FLIGHT","TELMU"],"2457":["Amps","FLIGHT"],"2458":["TELMU"],"2459":["FLIGHT"],"2460":["TELMU"],"2461":["FLIGHT","EECOM"],"2462":["TELMU"],"2463":["FLIGHT","TELMU"],"2464":["TELMU"],"2465":["FLIGHT"],"2466":["TELMU"],"2467":["FLIGHT"],"2468":["FLIGHT","INCO"],"2469":["FLIGHT","INCO"],"2470":["FDO","INCO"],"2471":["FLIGHT"],"2472":["INCO"],"2473":["FLIGHT"],"2474":["INCO"],"2475":["FLIGHT","FDO","RETRO"],"2476":["FLIGHT","GUIDO"],"2477":["FLIGHT","CONTROL"],"2478":["FLIGHT","CONTROL"],"2479":["FLIGHT","TELMU"],"2480":["FLIGHT","TELMU"],"2481":["FLIGHT","TELMU"],"2482":["FLIGHT","TELMU"],"2483":["FLIGHT"],"2484":["TELMU"],"2485":["FLIGHT","GNC"],"2486":["FLIGHT","GNC"],"2487":["FLIGHT","EECOM"],"2488":["EECOM"],"2489":["FLIGHT","CAPCOM"],"2490":["CAPCOM"],"2491":["PTC","FLIGHT"],"2492":["CAPCOM"],"2493":["FLIGHT"],"2494":["CAPCOM"],"2495":["FLIGHT"],"2496":["CAPCOM"],"2497":["FLIGHT","FDO","INCO"],"2498":["FLIGHT","FDO"],"2499":["FLIGHT"],"2500":["FLIGHT","FDO"],"2501":["FLIGHT"],"2502":["CAPCOM"],"2503":["FLIGHT"],"2504":["CAPCOM"],"2505":["FLIGHT"],"2506":["CAPCOM"],"2507":["FLIGHT"],"2509":["FLIGHT","INCO"],"2510":["FLIGHT","AFD","INCO"],"2511":["FLIGHT","AFD"],"2512":["FLIGHT"],"2514":["CSM","FLIGHT"],"2516":["FLIGHT","NETWORK"],"2517":["210","NETWORK"],"2518":["FLIGHT"],"2519":["NETWORK"],"2520":["FLIGHT"],"2521":["FLIGHT"],"2522":["FLIGHT","NETWORK"],"2523":["FLIGHT","INCO"],"2524":["FLIGHT","CAPCOM"],"2525":["CAPCOM"],"2526":["FLIGHT"],"2527":["FLIGHT","INCO"],"2528":["FLIGHT"],"2529":["INCO"],"2530":["FLIGHT","CAPCOM"],"2531":["FLIGHT","INCO"],"2532":["FLIGHT","INCO"],"2533":["CSM"],"2534":["FLIGHT","EECOM"],"2535":["FLIGHT","EECOM"],"2536":["FLIGHT"],"2537":["EECOM"],"2538":["FLIGHT","CAPCOM"],"2539":["FLIGHT","CAPCOM"],"2540":["PTC","FLIGHT"],"2541":["CAPCOM"],"2542":["FLIGHT"],"2543":["FLIGHT"],"2544":["CAPCOM"],"2545":["FLIGHT"],"2546":["FLIGHT","TELMU"],"2547":["FLIGHT","TELMU"],"2548":["TELMU"],"2549":["FLIGHT","TELMU"],"2550":["TELMU"],"2551":["FLIGHT","TELMU"],"2552":["TELMU"],"2553":["FLIGHT"],"2554":["TELMU"],"2555":["FLIGHT"],"2556":["FLIGHT"],"2557":["FLIGHT","TELMU"],"2558":["FLIGHT"],"2559":["TELMU"],"2560":["FLIGHT"],"2561":["TELMU"],"2562":["TELMU"],"2563":["FLIGHT"],"2564":["TELMU"],"2565":["FLIGHT"],"2566":["Amps","TELMU"],"2567":["FLIGHT"],"2568":["Amps","TELMU"],"2569":["FLIGHT","CONTROL"],"2570":["CONTROL"],"2571":["FLIGHT"],"2572":["CONTROL"],"2573":["FLIGHT"],"2574":["CONTROL"],"2575":["FLIGHT"],"2576":["CONTROL"],"2577":["FLIGHT"],"2578":["FLIGHT"],"2579":["Attitude","FLIGHT","TELMU"],"2580":["CONTROL"],"2581":["FLIGHT","TELMU"],"2582":["CONTROL"],"2583":["FLIGHT","CAPCOM"],"2584":["FLIGHT"],"2585":["FLIGHT","TELMU"],"2586":["FLIGHT","TELMU"],"2587":["FLIGHT","CONTROL"],"2588":["CONTROL"],"2589":["FLIGHT"],"2590":["CONTROL"],"2591":["FLIGHT"],"2592":["Rates","FLIGHT","CONTROL"],"2593":["P52","FLIGHT"],"2594":["CONTROL"],"2595":["FLIGHT","CAPCOM"],"2596":["CAPCOM"],"2597":["FLIGHT"],"2598":["CAPCOM"],"2599":["AOT","FLIGHT"],"2600":["CAPCOM"],"2601":["AOT","Current","FLIGHT"],"2602":["FLIGHT","CONTROL"],"2603":["FLIGHT","CONTROL"],"2604":["FLIGHT"],"2605":["FLIGHT","GUIDO"],"2606":["FLIGHT","INCO"],"2607":["FLIGHT","INCO"],"2608":["FLIGHT","INCO"],"2609":["FLIGHT"],"2610":["INCO"],"2611":["FLIGHT"],"2612":["FLIGHT"],"2613":["INCO"],"2614":["FLIGHT"],"2615":["FLIGHT","CAPCOM"],"2616":["FLIGHT","INCO"],"2617":["FLIGHT"],"2618":["FLIGHT","INCO"],"2619":["FLIGHT"],"2620":["INCO"],"2621":["FLIGHT"],"2622":["FLIGHT","CAPCOM"],"2623":["INCO"],"2624":["FLIGHT","CAPCOM"],"2625":["INCO"],"2626":["FLIGHT"],"2627":["INCO"],"2628":["FLIGHT"],"2629":["INCO"],"2630":["FLIGHT"],"2631":["INCO"],"2632":["INCO"],"2633":["INCO"],"2634":["FLIGHT"],"2635":["INCO"],"2636":["FLIGHT","TELMU"],"2637":["FLIGHT","TELMU"],"2638":["FLIGHT"],"2639":["TELMU"],"2640":["Attitude","PTC","FLIGHT","CONTROL"],"2641":["TELMU"],"2642":["FLIGHT","CONTROL"],"2643":["FLIGHT","CONTROL"],"2644":["FLIGHT"],"2645":["Attitude","CONTROL"],"2646":["CONTROL"],"2647":["FLIGHT","TELMU"],"2648":["FLIGHT"],"2649":["O2","TELMU"],"2650":["FLIGHT"],"2651":["TELMU"],"2652":["FLIGHT","INCO"],"2653":["FLIGHT","FDO","INCO"],"2654":["FLIGHT"],"2655":["INCO"],"2656":["FLIGHT"],"2657":["O2","FLIGHT","CAPCOM"],"2658":["FLIGHT"],"2659":["FLIGHT","CONTROL","GNC"],"2660":["CONTROL"],"2661":["PTC","FLIGHT"],"2662":["FLIGHT","CONTROL"],"2663":["FLIGHT"],"2664":["FLIGHT","INCO"],"2665":["FLIGHT"],"2666":["INCO"],"2667":["FLIGHT"],"2668":["FLIGHT","TELMU"],"2669":["FLIGHT","TELMU"],"2670":["Amps","FLIGHT"],"2671":["Amps","TELMU"],"2672":["FLIGHT"],"2673":["TELMU"],"2674":["Amps","FLIGHT","TELMU"],"2675":["Amps","FLIGHT"],"2676":["TELMU"],"2677":["FLIGHT"],"2678":["TELMU"],"2679":["FLIGHT"],"2680":["TELMU"],"2681":["FLIGHT","INCO"],"2682":["FLIGHT","INCO"],"2683":["FLIGHT","INCO"],"2684":["FLIGHT","INCO"],"2685":["FLIGHT"],"2686":["FLIGHT"],"2687":["FLIGHT","INCO"],"2688":["FLIGHT"],"2689":["INCO"],"2690":["FLIGHT"],"2691":["INCO"],"2692":["Pitch","FLIGHT"],"2693":["Roll","Yaw","INCO"],"2694":["Roll"],"2695":["INCO"],"2696":["Roll","FLIGHT"],"2697":["FLIGHT","CONTROL"],"2698":["FLIGHT"],"2699":["CONTROL"],"2700":["FLIGHT"],"2701":["CONTROL"],"2702":["FLIGHT","TELMU"],"2703":["FLIGHT"],"2704":["TELMU"],"2705":["FLIGHT","CAPCOM","INCO"],"2706":["INCO"],"2707":["FLIGHT","CAPCOM"],"2708":["FLIGHT","TELMU"],"2709":["FLIGHT"],"2710":["TELMU"],"2711":["FLIGHT"],"2712":["INCO"],"2713":["O2","FLIGHT","CAPCOM","CONTROL"],"2714":["CONTROL"],"2715":["FLIGHT"],"2716":["CONTROL"],"2717":["FLIGHT"],"2718":["CONTROL"],"2719":["PTC","FLIGHT","CONTROL"],"2720":["CAPCOM","INCO"],"2721":["FLIGHT","CAPCOM"],"2722":["CAPCOM"],"2723":["FLIGHT"],"2724":["FLIGHT"],"2725":["INCO"],"2726":["FLIGHT"],"2727":["INCO"],"2728":["CAPCOM"],"2729":["FLIGHT","INCO"],"2730":["INCO"],"2731":["FLIGHT"],"2732":["FLIGHT","CAPCOM"],"2733":["FLIGHT","CAPCOM"],"2734":["O2","FLIGHT"],"2735":["FLIGHT","INCO"],"2736":["FLIGHT","INCO"],"2737":["FLIGHT"],"2738":["FLIGHT","INCO"],"2739":["FLIGHT","INCO"],"2740":["INCO"],"2741":["FLIGHT","CONTROL"],"2742":["FLIGHT"],"2743":["P52","FLIGHT","CAPCOM"],"2744":["CAPCOM"],"2745":["FLIGHT","INCO"],"2746":["FLIGHT","INCO"],"2747":["FLIGHT"],"2748":["INCO"],"2749":["FLIGHT"],"2750":["INCO"],"2751":["FLIGHT","INCO"],"2752":["FLIGHT"],"2753":["FLIGHT","INCO"],"2754":["FLIGHT"],"2755":["FLIGHT"],"2756":["FLIGHT","INCO"],"2757":["FLIGHT","INCO"],"2758":["FLIGHT","CAPCOM"],"2759":["FLIGHT"],"2760":["FLIGHT"],"2761":["Attitude"],"2762":["FLIGHT","INCO"],"2763":["FLIGHT","CONTROL"],"2764":["FLIGHT","CONTROL"],"2765":["FLIGHT"],"2766":["FLIGHT","TELMU"],"2767":["FLIGHT"],"2768":["TELMU"],"2769":["FLIGHT"],"2770":["FLIGHT"],"2771":["FLIGHT","TELMU"],"2772":["FLIGHT","TELMU"],"2773":["FLIGHT","TELMU"],"2774":["FLIGHT","TELMU"],"2775":["FLIGHT","TELMU"],"2776":["FLIGHT","TELMU"],"2777":["FLIGHT"],"2778":["Amps","TELMU"],"2779":["FLIGHT"],"2780":["TELMU"],"2781":["FLIGHT"],"2782":["CAPCOM"],"2783":["FLIGHT","INCO"],"2784":["FLIGHT","INCO"],"2785":["INCO"],"2786":["FLIGHT","INCO"],"2787":["FLIGHT"],"2788":["INCO"],"2789":["FLIGHT"],"2790":["INCO"],"2791":["FLIGHT"],"2792":["INCO"],"2793":["FLIGHT"],"2794":["FLIGHT"],"2795":["CAPCOM"],"2796":["INCO"],"2797":["FLIGHT"],"2798":["CAPCOM"],"2799":["FLIGHT","INCO"],"2800":["FLIGHT","INCO"],"2801":["FLIGHT","INCO"],"2802":["INCO"],"2803":["FLIGHT"],"2804":["INCO"],"2805":["FLIGHT","CAPCOM"],"2806":["FLIGHT","INCO"],"2807":["FLIGHT","CONTROL"],"2808":["CONTROL"],"2809":["PTC","FLIGHT"],"2810":["CONTROL"],"2811":["FLIGHT"],"2812":["Attitude","CONTROL"],"2813":["FLIGHT"],"2814":["PTC","CONTROL"],"2815":["Attitude","PTC","CONTROL"],"2816":["FLIGHT"],"2817":["CAPCOM"],"2818":["Attitude","FLIGHT"],"2819":["PTC","FLIGHT"],"2820":["CAPCOM","PTC"],"2821":["FLIGHT"],"2822":["PTC","FLIGHT"],"2823":["CONTROL"],"2824":["FLIGHT","CONTROL"],"2825":["FLIGHT"],"2826":["FLIGHT"],"2827":["INCO"],"2828":["FLIGHT","FDO"],"2829":["FLIGHT"],"2830":["FDO"],"2831":["FLIGHT"],"2832":["FDO"],"2833":["FLIGHT"],"2834":["CSM","FDO"],"2835":["FLIGHT"],"2836":["FDO"],"2837":["FLIGHT"],"2838":["FDO"],"2839":["FLIGHT"],"2840":["FDO"],"2841":["FLIGHT"],"2842":["FLIGHT","GUIDO"],"2843":["FLIGHT"],"2844":["GUIDO"],"2845":["FLIGHT"],"2846":["FLIGHT","FDO"],"2847":["FLIGHT","FDO"],"2848":["FLIGHT"],"2849":["FLIGHT","FDO"],"2850":["FLIGHT"],"2851":["FDO"],"2852":["FLIGHT","EECOM","TELMU"],"2853":["FLIGHT","EECOM"],"2854":["FLIGHT","TELMU"],"2855":["FLIGHT"],"2856":["TELMU"],"2857":["FLIGHT"],"2858":["TELMU"],"2859":["FLIGHT","INCO"],"2860":["FLIGHT"],"2861":["FLIGHT","TELMU"],"2862":["FLIGHT"],"2863":["TELMU"],"2864":["FLIGHT"],"2865":["TELMU"],"2866":["FLIGHT"],"2867":["TELMU"],"2868":["FLIGHT"],"2870":["TELMU"],"2872":["FLIGHT"],"2873":["TELMU"],"2874":["FLIGHT"],"2875":["FLIGHT","INCO"],"2876":["FLIGHT"],"2877":["INCO"],"2878":["FLIGHT"],"2879":["FLIGHT","FDO"],"2880":["FDO"],"2881":["FLIGHT"],"2882":["FLIGHT","GUIDO","Attitude"],"2883":["FLIGHT"],"2884":["FLIGHT"],"2885":["GUIDO"],"2886":["FLIGHT","INCO"],"2887":["INCO"],"2888":["FLIGHT","INCO"],"2889":["FLIGHT","INCO"],"2890":["FLIGHT","FDO"],"2891":["FLIGHT","FDO"],"2892":["FLIGHT"],"2893":["FLIGHT","FDO"],"2894":["FLIGHT"],"2895":["FLIGHT"],"2896":["FDO"],"2897":["FLIGHT"],"2898":["FDO"],"2899":["FLIGHT","CONTROL"],"2900":["FLIGHT","CONTROL"],"2901":["FLIGHT"],"2902":["CONTROL"],"2903":["CONTROL"],"2904":["FLIGHT"],"2905":["CONTROL"],"2906":["FLIGHT","INCO"],"2907":["FLIGHT"],"2908":["INCO"],"2909":["FLIGHT"],"2910":["FLIGHT"],"2911":["FLIGHT"],"2912":["FLIGHT"],"2913":["FLIGHT"],"2914":["FLIGHT"],"2915":["FLIGHT","FDO"],"2916":["FLIGHT"],"2917":["CAPCOM"],"2918":["FLIGHT"],"2919":["FLIGHT"],"2920":["FLIGHT","FDO"],"2921":["FLIGHT","FDO"],"2922":["CONTROL"],"2923":["FLIGHT"],"2924":["FLIGHT","FDO"],"2925":["FDO"],"2926":["FLIGHT"],"2927":["FLIGHT"],"2928":["FLIGHT","CAPCOM"],"2929":["FLIGHT"],"2930":["FLIGHT","CAPCOM"],"2931":["CAPCOM"],"2932":["FLIGHT","FDO"],"2933":["FLIGHT","FDO"],"2934":["FLIGHT","FDO"],"2935":["Attitude","FLIGHT"],"2936":["FDO"],"2937":["FLIGHT"],"2938":["FDO"],"2939":["FLIGHT","CONTROL","GNC"],"2940":["CONTROL"],"2941":["FLIGHT","GNC"],"2942":["FLIGHT","GNC"],"2943":["RCS","FLIGHT"],"2944":["FLIGHT","CAPCOM"],"2945":["FLIGHT"],"2946":["CAPCOM"],"2947":["FLIGHT"],"2948":["FLIGHT","CONTROL","TELMU"],"2949":["CONTROL"],"2950":["TELMU"],"2951":["FLIGHT"],"2952":["FLIGHT","GUIDO"],"2953":["FLIGHT"],"2954":["TELMU"],"2955":["CAPCOM"],"2956":["FLIGHT","INCO"],"2957":["FLIGHT"],"2958":["INCO"],"2959":["FLIGHT"],"2960":["INCO"],"2961":["FLIGHT"],"2962":["INCO"],"2963":["CAPCOM"],"2964":["FLIGHT","CONTROL","TELMU"],"2965":["FLIGHT","CONTROL"],"2966":["CAPCOM"],"2967":["TELMU"],"2968":["TELMU"],"2969":["FLIGHT","TELMU"],"2970":["FLIGHT","TELMU"],"2971":["Inverter","TELMU"],"2972":["FLIGHT"],"2973":["FLIGHT","TELMU"],"2974":["Inverter","TELMU"],"2975":["Inverter","FLIGHT","CAPCOM"],"2976":["TELMU"],"2977":["TELMU"],"2978":["FLIGHT"],"2979":["TELMU"],"2980":["FLIGHT","TELMU"],"2981":["FLIGHT"],"2982":["TELMU"],"2983":["TELMU"],"2984":["FLIGHT"],"2985":["TELMU"],"2986":["FLIGHT","CONTROL"],"2987":["FLIGHT"],"2988":["CONTROL"],"2989":["FLIGHT"],"2990":["CONTROL"],"2991":["FLIGHT"],"2992":["FLIGHT","RETRO"],"2993":["FLIGHT","INCO"],"2994":["FLIGHT","RETRO"],"2995":["FLIGHT","RETRO"],"2996":["FLIGHT","CONTROL"],"2997":["FLIGHT","CONTROL"],"2998":["FLIGHT","INCO"],"2999":["FLIGHT"],"3000":["FLIGHT","CONTROL"],"3001":["FLIGHT","CONTROL"],"3002":["CONTROL"],"3003":["CAPCOM"],"3004":["FLIGHT"],"3005":["TELMU"],"3006":["CONTROL"],"3007":["FLIGHT","CONTROL"],"3008":["CONTROL"],"3009":["FLIGHT"],"3010":["FLIGHT","CONTROL"],"3011":["AC bus","CONTROL"],"3012":["CAPCOM"],"3013":["CONTROL"],"3014":["CONTROL"],"3015":["FLIGHT"],"3016":["CONTROL"],"3017":["FLIGHT"],"3018":["CAPCOM"],"3019":["FLIGHT"],"3021":["CAPCOM"],"3022":["FLIGHT"],"3023":["FLIGHT"],"3024":["CAPCOM"],"3025":["FLIGHT"],"3026":["CAPCOM"],"3027":["FLIGHT","CONTROL","TELMU"],"3028":["FLIGHT","CONTROL","TELMU"],"3029":["TELMU"],"3030":["FLIGHT"],"3031":["TELMU"],"3032":["FLIGHT","CONTROL"],"3033":["FLIGHT","CONTROL"],"3034":["FLIGHT"],"3035":["CONTROL"],"3036":["FLIGHT"],"3037":["CONTROL"],"3038":["FLIGHT"],"3039":["CONTROL"],"3040":["CAPCOM"],"3041":["FLIGHT"],"3042":["CAPCOM"],"3043":["FLIGHT"],"3044":["CAPCOM"],"3045":["FLIGHT"],"3046":["FLIGHT"],"3047":["FLIGHT"],"3048":["FLIGHT"],"3049":["FLIGHT","GUIDO"],"3050":["FLIGHT"],"3051":["GUIDO"],"3052":["FLIGHT"],"3053":["GUIDO"],"3054":["FLIGHT"],"3055":["GUIDO"],"3056":["FLIGHT"],"3057":["CONTROL","GUIDO"],"3058":["FLIGHT"],"3059":["CONTROL"],"3060":["CAPCOM"],"3061":["FLIGHT"],"3062":["CONTROL"],"3063":["RCS","GUIDO"],"3064":["FLIGHT"],"3065":["FLIGHT"],"3066":["FLIGHT","GUIDO"],"3067":["FLIGHT"],"3068":["GUIDO"],"3069":["FLIGHT"],"3070":["GUIDO"],"3071":["FLIGHT"],"3072":["FLIGHT","GUIDO"],"3073":["FLIGHT"],"3074":["GUIDO"],"3075":["FLIGHT"],"3076":["CAPCOM"],"3077":["FLIGHT","TELMU"],"3078":["TELMU"],"3079":["FLIGHT"],"3080":["CAPCOM"],"3081":["FLIGHT"],"3082":["CONTROL"],"3083":["TELMU"],"3084":["FLIGHT"],"3085":["CONTROL"],"3086":["FLIGHT"],"3087":["CAPCOM"],"3088":["FLIGHT","CONTROL"],"3089":["FLIGHT","CONTROL"],"3090":["FLIGHT","CONTROL"],"3091":["FLIGHT"],"3092":["CONTROL"],"3093":["FLIGHT"],"3094":["CONTROL"],"3095":["FLIGHT"],"3096":["CONTROL"],"3097":["CAPCOM"],"3098":["INCO"],"3099":["FLIGHT"],"3100":["INCO"],"3101":["FLIGHT"],"3102":["CAPCOM"],"3103":["INCO"],"3104":["FLIGHT"],"3105":["INCO"],"3106":["FLIGHT"],"3107":["INCO"],"3108":["FLIGHT"],"3109":["FLIGHT"],"3111":["FLIGHT"],"3113":["FLIGHT"],"3114":["FLIGHT","CAPCOM"],"3115":["FLIGHT","CONTROL","INCO","TELMU"],"3116":["CONTROL"],"3117":["FLIGHT"],"3118":["CONTROL"],"3119":["CONTROL"],"3120":["FLIGHT"],"3121":["Helium","CONTROL"],"3122":["FLIGHT"],"3123":["CONTROL"],"3124":["FLIGHT"],"3125":["TELMU"],"3126":["TELMU"],"3127":["FLIGHT","TELMU"],"3128":["TELMU"],"3129":["FLIGHT"],"3130":["FLIGHT"],"3131":["FLIGHT"],"3132":["FLIGHT"],"3134":["FLIGHT","CONTROL"],"3135":["CONTROL"],"3136":["FLIGHT"],"3137":["CONTROL"],"3138":["FLIGHT","FDO"],"3139":["FLIGHT","FDO"],"3140":["FLIGHT"],"3141":["FDO"],"3142":["FLIGHT","CONTROL"],"3143":["CONTROL"],"3144":["FLIGHT"],"3145":["CONTROL"],"3146":["FLIGHT"],"3147":["CONTROL"],"3148":["CAPCOM"],"3149":["CONTROL"],"3150":["FLIGHT"],"3151":["TELMU"],"3152":["FLIGHT"],"3153":["Current","TELMU"],"3154":["Current","FLIGHT","CAPCOM"],"3155":["FLIGHT"],"3156":["FLIGHT","INCO"],"3157":["INCO"],"3158":["FLIGHT","INCO"],"3159":["INCO"],"3160":["FLIGHT"],"3161":["INCO"],"3162":["FLIGHT"],"3163":["INCO"],"3164":["FLIGHT"],"3165":["INCO"],"3166":["FLIGHT","CAPCOM"],"3167":["FLIGHT","GUIDO"],"3168":["FLIGHT"],"3169":["FLIGHT","GUIDO"],"3170":["FLIGHT"],"3171":["FLIGHT","GUIDO"],"3172":["FLIGHT"],"3173":["GUIDO"],"3174":["FLIGHT"],"3175":["FLIGHT"],"3176":["FLIGHT","GUIDO"],"3177":["DPS","FLIGHT"],"3178":["FLIGHT","FDO","GUIDO"],"3179":["FLIGHT"],"3180":["GUIDO"],"3181":["FLIGHT"],"3182":["GUIDO"],"3183":["GUIDO"],"3184":["FLIGHT"],"3185":["TELMU"],"3186":["FLIGHT","TELMU"],"3187":["TELMU"],"3188":["FLIGHT"],"3189":["P00","FLIGHT","CAPCOM"],"3190":["FLIGHT"],"3191":["FLIGHT"],"3192":["FLIGHT","GUIDO","INCO"],"3193":["FLIGHT"],"3194":["GUIDO"],"3195":["FLIGHT"],"3196":["FLIGHT","TELMU"],"3197":["FLIGHT"],"3198":["TELMU"],"3199":["FLIGHT"],"3200":["FLIGHT","CONTROL"],"3201":["FLIGHT"],"3202":["CONTROL"],"3203":["TELMU"],"3204":["FLIGHT"],"3205":["ECA","CAPCOM"],"3206":["TELMU"],"3207":["FLIGHT","TELMU"],"3208":["TELMU"],"3209":["FLIGHT"],"3210":["CAPCOM"],"3211":["FLIGHT","CONTROL"],"3212":["CONTROL"],"3213":["FLIGHT","TELMU"],"3214":["TELMU"],"3215":["FLIGHT"],"3216":["GUIDO"],"3217":["FLIGHT","INCO"],"3218":["INCO"],"3219":["FLIGHT","CAPCOM"],"3220":["CAPCOM"],"3221":["FLIGHT"],"3222":["CAPCOM"],"3223":["FLIGHT"],"3224":["CAPCOM"],"3225":["FLIGHT"],"3226":["Attitude","FLIGHT","INCO"],"3227":["FLIGHT","GUIDO"],"3228":["FLIGHT"],"3229":["GUIDO"],"3230":["FLIGHT","CAPCOM"],"3231":["FLIGHT","CONTROL"],"3232":["FLIGHT"],"3233":["Attitude","CONTROL"],"3234":["FLIGHT"],"3235":["CONTROL"],"3236":["FLIGHT","GUIDO"],"3237":["FLIGHT"],"3238":["FLIGHT","CONTROL"],"3239":["FLIGHT","CONTROL"],"3240":["FLIGHT"],"3241":["Attitude","CONTROL"],"3242":["FLIGHT","CONTROL"],"3243":["FLIGHT","CAPCOM"],"3244":["FLIGHT"],"3245":["FLIGHT"],"3246":["FLIGHT"],"3247":["CAPCOM"],"3248":["FLIGHT"],"3249":["FLIGHT","GUIDO"],"3250":["FLIGHT"],"3251":["FLIGHT"],"3252":["GUIDO"],"3253":["FLIGHT"],"3254":["FLIGHT"],"3255":["FLIGHT","GUIDO"],"3256":["FLIGHT"],"3257":["CAPCOM"],"3258":["FLIGHT"],"3259":["CAPCOM"],"3260":["FLIGHT","CAPCOM"],"3261":["FLIGHT"],"3262":["TELMU"],"3263":["FLIGHT"],"3264":["CAPCOM"],"3265":["CMC","FLIGHT"],"3266":["FLIGHT","GUIDO"],"3267":["FLIGHT"],"3268":["FLIGHT"],"3269":["FLIGHT"],"3271":["FLIGHT"],"3272":["FLIGHT"],"3273":["CAPCOM"],"3274":["FLIGHT"],"3275":["CAPCOM"],"3276":["FLIGHT","CONTROL"],"3277":["CONTROL"],"3279":["FLIGHT"],"3280":["FLIGHT"],"3281":["TELMU"],"3282":["FLIGHT","TELMU"],"3283":["CONTROL"],"3284":["CAPCOM"],"3285":["CONTROL"],"3286":["FLIGHT"],"3287":["FLIGHT"],"3288":["FLIGHT"],"3289":["FLIGHT"],"3290":["FLIGHT"],"3291":["GUIDO"],"3292":["FLIGHT","GUIDO"],"3293":["CAPCOM"],"3294":["FLIGHT","CAPCOM"],"3295":["FLIGHT"],"3296":["FLIGHT","CONTROL"],"3297":["FLIGHT"],"3298":["CONTROL"],"3299":["DPS","CAPCOM"],"3300":["FLIGHT","GUIDO"],"3301":["CONTROL"],"3302":["FLIGHT"],"3303":["GUIDO"],"3304":["FLIGHT"],"3305":["GUIDO"],"3306":["FLIGHT"],"3307":["GUIDO"],"3308":["FLIGHT"],"3309":["CAPCOM"],"3310":["FLIGHT"],"3311":["FLIGHT","CONTROL"],"3312":["CONTROL"],"3313":["FLIGHT"],"3314":["CONTROL"],"3315":["FLIGHT"],"3316":["FLIGHT","GUIDO"],"3317":["FLIGHT","CONTROL"],"3318":["FLIGHT"],"3319":["CONTROL"],"3320":["FLIGHT","CAPCOM"],"3321":["CAPCOM"],"3322":["FLIGHT"],"3323":["CAPCOM"],"3324":["FLIGHT"],"3325":["CAPCOM"],"3326":["FLIGHT","CONTROL"],"3327":["CAPCOM"],"3328":["FLIGHT","CONTROL"],"3329":["FLIGHT"],"3330":["CONTROL"],"3331":["FLIGHT","CONTROL"],"3332":["FLIGHT","CONTROL"],"3333":["FLIGHT"],"3334":["FLIGHT","CONTROL"],"3335":["FLIGHT","CAPCOM"],"3336":["FLIGHT","CONTROL"],"3337":["FLIGHT","CONTROL"],"3338":["FLIGHT"],"3339":["GUIDO"],"3340":["DPS","FLIGHT","CONTROL"],"3341":["FLIGHT"],"3342":["CONTROL"],"3343":["FLIGHT"],"3344":["CONTROL"],"3345":["FLIGHT"],"3346":["CONTROL"],"3347":["ACA","Jets","CONTROL"],"3348":["FLIGHT"],"3349":["Attitude","CONTROL"],"3350":["Attitude","Jets","CONTROL"],"3351":["FLIGHT","CONTROL"],"3352":["CAPCOM"],"3353":["CONTROL"],"3354":["FLIGHT"],"3355":["FLIGHT","CONTROL"],"3356":["FLIGHT"],"3357":["CONTROL"],"3358":["FLIGHT","CAPCOM"],"3359":["Jets","CAPCOM"],"3360":["Jets","CONTROL"],"3361":["CONTROL"],"3362":["FLIGHT"],"3363":["CONTROL"],"3364":["FLIGHT"],"3365":["CONTROL"],"3366":["FLIGHT"],"3367":["FLIGHT","CONTROL"],"3368":["CONTROL"],"3369":["CONTROL"],"3370":["FLIGHT"],"3371":["CONTROL"],"3372":["FLIGHT"],"3373":["FLIGHT"],"3374":["CONTROL"],"3375":["FLIGHT"],"3376":["CONTROL"],"3377":["FLIGHT"],"3378":["FLIGHT"],"3379":["FLIGHT","CONTROL"],"3380":["FLIGHT"],"3381":["FLIGHT","CONTROL"],"3382":["FLIGHT"],"3383":["CONTROL"],"3384":["FLIGHT"],"3385":["CONTROL"],"3386":["FLIGHT"],"3387":["GUIDO"],"3388":["FLIGHT"],"3389":["FLIGHT","GUIDO"],"3390":["FLIGHT"],"3391":["FLIGHT","GUIDO"],"3392":["CAPCOM"],"3393":["FLIGHT"],"3394":["GUIDO"],"3395":["FLIGHT"],"3396":["CAPCOM"],"3397":["FLIGHT"],"3398":["CONTROL"],"3399":["FLIGHT","FDO"],"3400":["FLIGHT"],"3401":["FDO"],"3402":["FLIGHT"],"3403":["FLIGHT","CONTROL"],"3404":["FLIGHT"],"3405":["CONTROL"],"3406":["FLIGHT"],"3407":["CONTROL"],"3408":["FLIGHT"],"3409":["CONTROL"],"3410":["FLIGHT"],"3411":["CONTROL"],"3412":["FLIGHT","CAPCOM"],"3413":["CONTROL"],"3414":["CONTROL"],"3415":["FLIGHT"],"3416":["FLIGHT"],"3417":["DPS","FLIGHT"],"3418":["FLIGHT"],"3420":["FLIGHT"],"3421":["FLIGHT"],"3422":["CAPCOM"],"3424":["CONTROL"],"3425":["FLIGHT"],"3426":["CONTROL"],"3427":["DPS","CONTROL"],"3428":["CONTROL"],"3429":["Jet","Ullage","CAPCOM"],"3430":["FLIGHT","CONTROL"],"3431":["FLIGHT","CONTROL"],"3432":["FLIGHT"],"3433":["CONTROL"],"3434":["CONTROL"],"3435":["FLIGHT"],"3436":["CONTROL"],"3437":["FLIGHT","FDO","RETRO"],"3438":["FLIGHT","RETRO"],"3439":["Jet","FLIGHT"],"3440":["RETRO"],"3441":["FDO"],"3442":["Jet","FLIGHT","CAPCOM"],"3443":["CAPCOM"],"3444":["CONTROL"],"3445":["FLIGHT"],"3446":["CAPCOM"],"3447":["CONTROL"],"3448":["FLIGHT","CONTROL"],"3449":["FLIGHT"],"3450":["CONTROL"],"3451":["FLIGHT"],"3452":["FLIGHT"],"3453":["CAPCOM"],"3454":["FLIGHT"],"3455":["CONTROL"],"3456":["CONTROL"],"3457":["FLIGHT"],"3458":["CONTROL"],"3459":["FLIGHT"],"3460":["CONTROL"],"3461":["CAPCOM"],"3462":["FLIGHT","CONTROL"],"3463":["CONTROL"],"3464":["FLIGHT"],"3465":["FLIGHT"],"3466":["FLIGHT","CONTROL"],"3467":["FLIGHT"],"3468":["CONTROL"],"3469":["FLIGHT"],"3470":["FLIGHT","CONTROL"],"3471":["FLIGHT"],"3472":["CONTROL"],"3473":["FLIGHT","CAPCOM"],"3474":["DPS","CAPCOM"],"3475":["CONTROL"],"3476":["FLIGHT"],"3477":["CAPCOM"],"3478":["Jet","Ullage","FLIGHT","CONTROL"],"3479":["FLIGHT"],"3480":["CONTROL"],"3481":["FLIGHT"],"3482":["CONTROL"],"3483":["Jets","FLIGHT"],"3484":["CAPCOM"],"3485":["FLIGHT"],"3486":["AFD"],"3487":["FLIGHT"],"3488":["GUIDO"],"3489":["GUIDO"],"3490":["FLIGHT"],"3491":["GUIDO"],"3492":["FLIGHT"],"3493":["FLIGHT","CONTROL"],"3494":["CONTROL"],"3495":["FLIGHT"],"3496":["FLIGHT","CONTROL"],"3497":["FLIGHT"],"3498":["FLIGHT","GUIDO"],"3499":["FLIGHT"],"3500":["GUIDO"],"3501":["GUIDO"],"3502":["FLIGHT"],"3503":["GUIDO"],"3504":["FLIGHT"],"3505":["FLIGHT","CONTROL"],"3506":["CONTROL"],"3507":["FLIGHT"],"3508":["FLIGHT","CONTROL"],"3509":["Attitude","FLIGHT","CAPCOM"],"3510":["FLIGHT"],"3511":["Attitude","FLIGHT","INCO"],"3512":["INCO"],"3513":["FLIGHT"],"3514":["INCO"],"3515":["FLIGHT"],"3516":["Attitude","CAPCOM"],"3517":["FLIGHT","GUIDO"],"3518":["FLIGHT"],"3519":["Attitude","CAPCOM"],"3520":["FLIGHT"],"3521":["FLIGHT"],"3522":["GUIDO"],"3523":["FLIGHT","CAPCOM"],"3524":["DSKY","CAPCOM"],"3525":["Pitch","Roll","Yaw","FLIGHT","GUIDO"],"3526":["FLIGHT"],"3527":["Attitude","Pitch","Roll","Yaw","GUIDO"],"3528":["DSKY","FLIGHT"],"3529":["GUIDO"],"3530":["FLIGHT"],"3531":["FLIGHT","GUIDO"],"3532":["Yaw","FLIGHT"],"3533":["Yaw","FLIGHT","GUIDO"],"3534":["CAPCOM","Attitude"],"3535":["Yaw","GUIDO"],"3536":["FLIGHT"],"3537":["Yaw","FLIGHT"],"3538":["FLIGHT"],"3539":["FLIGHT","GUIDO"],"3540":["FLIGHT"],"3541":["FLIGHT","INCO"],"3542":["INCO"],"3543":["FLIGHT","CONTROL"],"3544":["GUIDO"],"3545":["CONTROL"],"3546":["FLIGHT"],"3547":["FLIGHT","GUIDO"],"3548":["FLIGHT"],"3549":["GUIDO"],"3550":["FLIGHT"],"3551":["GUIDO"],"3552":["FLIGHT"],"3553":["GUIDO"],"3554":["FLIGHT"],"3555":["Attitude","CONTROL","GUIDO"],"3556":["FLIGHT","CONTROL"],"3557":["GUIDO"],"3558":["FLIGHT"],"3559":["CONTROL","GUIDO"],"3560":["FLIGHT"],"3561":["Attitude","CONTROL","GUIDO"],"3562":["FLIGHT"],"3563":["Attitude","FLIGHT","CAPCOM"],"3564":["Attitude","FLIGHT"],"3565":["Attitude","FLIGHT","GUIDO"],"3566":["FLIGHT"],"3567":["GUIDO"],"3568":["FLIGHT"],"3569":["Attitude","GUIDO"],"3570":["FLIGHT"],"3571":["GUIDO"],"3572":["FLIGHT"],"3573":["Yaw","GUIDO"],"3574":["FLIGHT"],"3575":["FLIGHT"],"3576":["Attitude"],"3577":["FLIGHT"],"3579":["DSKY","FLIGHT"],"3580":["FLIGHT"],"3581":["GUIDO"],"3582":["Attitude","DSKY","FLIGHT"],"3583":["FLIGHT"],"3584":["Pitch","Roll","Yaw","GUIDO"],"3585":["FLIGHT"],"3586":["FLIGHT","GUIDO"],"3587":["CAPCOM"],"3588":["FLIGHT"],"3589":["FLIGHT"],"3590":["Attitude","CAPCOM"],"3591":["Attitude","FLIGHT"],"3592":["Attitude","FLIGHT","GUIDO"],"3593":["FLIGHT"],"3594":["FLIGHT"],"3595":["FLIGHT","GUIDO"],"3596":["Attitude","FLIGHT"],"3597":["FLIGHT","GUIDO"],"3598":["FLIGHT","GUIDO"],"3599":["FLIGHT"],"3600":["GUIDO"],"3601":["FLIGHT"],"3602":["GUIDO"],"3603":["GUIDO"],"3604":["GUIDO"],"3605":["FLIGHT","CONTROL"],"3606":["FLIGHT"],"3607":["CONTROL"],"3608":["FLIGHT"],"3609":["CONTROL"],"3610":["FLIGHT"],"3611":["CONTROL"],"3612":["Attitude","FLIGHT"],"3613":["CONTROL"],"3614":["CONTROL"],"3615":["FLIGHT","CAPCOM"],"3616":["FLIGHT","CAPCOM"],"3617":["CAPCOM"],"3618":["Attitude","Rates","FLIGHT","CONTROL"],"3619":["FLIGHT"],"3620":["CAPCOM"],"3621":["FLIGHT"],"3622":["GUIDO"],"3623":["FLIGHT"],"3624":["FLIGHT","TELMU"],"3625":["FLIGHT"],"3626":["TELMU"],"3627":["FLIGHT"],"3628":["FLIGHT","CAPCOM"],"3629":["FLIGHT"],"3630":["FLIGHT"],"3631":["CAPCOM"],"3632":["FLIGHT"],"3633":["FLIGHT"],"3634":["FLIGHT","CONTROL"],"3635":["FLIGHT","CONTROL"],"3636":["FLIGHT"],"3637":["CAPCOM"],"3638":["FLIGHT","CONTROL"],"3639":["FLIGHT"],"3640":["FLIGHT","CONTROL"],"3641":["FLIGHT"],"3642":["FLIGHT"],"3643":["CONTROL"],"3644":["FLIGHT","CAPCOM","CONTROL"],"3645":["FLIGHT","GUIDO"],"3646":["Ullage","FLIGHT"],"3647":["Ullage","FLIGHT","CONTROL"],"3648":["FLIGHT"],"3649":["FLIGHT","GUIDO"],"3650":["FLIGHT"],"3651":["GUIDO"],"3652":["FLIGHT","CAPCOM"],"3653":["FLIGHT","GUIDO"],"3654":["FLIGHT","GUIDO"],"3655":["FLIGHT"],"3656":["FLIGHT"],"3657":["CAPCOM"],"3658":["FLIGHT"],"3659":["FLIGHT","CAPCOM"],"3660":["FLIGHT"],"3661":["FLIGHT","CONTROL"],"3662":["FLIGHT"],"3663":["CONTROL"],"3664":["FLIGHT"],"3665":["CAPCOM"],"3666":["FLIGHT"],"3667":["CAPCOM"],"3668":["FLIGHT"],"3669":["FLIGHT","GUIDO"],"3670":["FLIGHT"],"3671":["FLIGHT"],"3672":["FLIGHT","GUIDO"],"3673":["FLIGHT"],"3674":["FLIGHT","GUIDO"],"3675":["FLIGHT"],"3676":["GUIDO"],"3677":["FLIGHT","CAPCOM"],"3678":["GUIDO"],"3679":["FLIGHT"],"3680":["DPS","GUIDO"],"3681":["FLIGHT"],"3682":["FLIGHT","CONTROL"],"3683":["Attitude","FLIGHT"],"3684":["Jets","FLIGHT","CONTROL"],"3685":["FLIGHT"],"3686":["CAPCOM"],"3687":["Ullage","FLIGHT"],"3688":["FLIGHT","GUIDO"],"3689":["FLIGHT"],"3690":["FLIGHT","GUIDO","DSKY"],"3691":["FLIGHT"],"3692":["GUIDO"],"3693":["FLIGHT","RETRO"],"3694":["FLIGHT"],"3695":["FLIGHT","RETRO"],"3696":["FLIGHT"],"3698":["FLIGHT","GUIDO"],"3699":["FLIGHT"],"3700":["FLIGHT","GUIDO"],"3701":["FLIGHT"],"3702":["CAPCOM"],"3703":["FLIGHT","CONTROL"],"3704":["CONTROL"],"3705":["FLIGHT"],"3706":["FLIGHT","CONTROL"],"3707":["FLIGHT"],"3708":["FLIGHT"],"3709":["FLIGHT","GUIDO"],"3710":["FLIGHT","CONTROL"],"3711":["FLIGHT","CONTROL"],"3712":["FLIGHT","TELMU"],"3713":["FLIGHT","TELMU"],"3714":["FLIGHT","INCO"],"3715":["FLIGHT","INCO"],"3716":["FLIGHT"],"3717":["FLIGHT","CONTROL"],"3718":["FLIGHT"],"3719":["CONTROL"],"3720":["FLIGHT"],"3721":["CONTROL"],"3722":["FLIGHT","CONTROL"],"3723":["CONTROL"],"3724":["FLIGHT"],"3725":["Ullage","CONTROL"],"3726":["CONTROL"],"3727":["CONTROL"],"3728":["Rates","CONTROL"],"3729":["Rates","FLIGHT"],"3730":["FLIGHT","CONTROL"],"3731":["FLIGHT"],"3732":["CONTROL"],"3733":["CONTROL"],"3734":["FLIGHT"],"3735":["CAPCOM"],"3736":["FLIGHT"],"3737":["FLIGHT","GUIDO"],"3738":["FLIGHT"],"3739":["GUIDO"],"3740":["FLIGHT"],"3741":["FLIGHT"],"3742":["GUIDO"],"3743":["FLIGHT","CAPCOM"],"3744":["FLIGHT"]}